Digital System Design/Assignments/part_1/projects_4/blocking.v
//File: blocking.v

`timescale 1 ns / 1 ns

module blocking (
	output reg [3:0] c, b,
	input [3:0] a,
	input clk   // Clock
	
);
always @(posedge clk) begin
	//b = a;
	c = b;
	//b = a;

	$display("阻塞赋值：c = %d, b = %d, a = %d. ", c, b, a);

end

always @(posedge clk) begin
	//b = a;
	a = b;
	//b = a;

	$display("阻塞赋值：c = %d, b = %d, a = %d. ", c, b, a);

end

endmodule

Digital System Design/Assignments/part_1/projects_4/nonblocking.v
//File: nonblocking.v

`timescale 1 ns / 1 ns

module nonblocking (
	output reg [3:0] c,
	output reg [3:0] b,
	input [3:0] a,
	input clk    // Clock

);
always @(posedge clk) begin
	b <= a;
	c <= b;

	$display("非阻塞赋值：c = %d, b = %d, a = %d. ", c, b, a);

end

endmodule

Digital System Design/Assignments/part_1/projects_4/born_test_tb.v
//File: born_test_tb.v

`timescale 1 ns / 1 ns

`include "blocking.v"
`include "nonblocking.v"

module born_test_tb;

	wire [3:0] p_c2, p_b2;
	wire [3:0] p_c1, p_b1;

	reg [3:0] p_a;
	reg p_clk;

	nonblocking m_nblk(.c(p_c2),
		.b(p_b2),
		.a(p_a),
		.clk(p_clk));

	blocking m_blk(.c(p_c1),
		.b(p_b1),
		.a(p_a),
		.clk(p_clk));

	initial
	begin
		$dumpfile("born.vcd");
		$dumpvars(0, born_test_tb);

		p_clk = 0;
		forever #50 p_clk = ~p_clk;
	end

	initial
	begin
		$display("At time: %tns", $time);
		p_a = 4'h3;
		#100 $display("At time: %tns", $time);
		p_a = 4'h7;
		#100 $display("At time: %tns", $time);
		p_a = 4'hf;
		#100 $display("At time: %tns", $time);
		p_a = 4'ha;
		#100 $display("At time: %tns", $time);
		p_a = 4'h2;

		#100 $stop;
	end

endmodule

Digital System Design/Assignments/part_1/projects_4/born.vcd
$date
	Sat Nov 30 19:21:45 2019
$end
$version
	Icarus Verilog
$end
$timescale
	1ns
$end
$scope module born_test_tb $end
$var wire 4 ! p_c2 [3:0] $end
$var wire 4 " p_c1 [3:0] $end
$var wire 4 # p_b2 [3:0] $end
$var wire 4 $ p_b1 [3:0] $end
$var reg 4 % p_a [3:0] $end
$var reg 1 & p_clk $end
$scope module m_blk $end
$var wire 4 ' a [3:0] $end
$var wire 1 & clk $end
$var reg 4 ( b [3:0] $end
$var reg 4 ) c [3:0] $end
$upscope $end
$scope module m_nblk $end
$var wire 4 * a [3:0] $end
$var wire 1 & clk $end
$var reg 4 + b [3:0] $end
$var reg 4 , c [3:0] $end
$upscope $end
$upscope $end
$enddefinitions $end
#0
$dumpvars
bx ,
bx +
b11 *
bx )
bx (
b11 '
0&
b11 %
bx $
bx #
bx "
bx !
$end
#50
b11 #
b11 +
b11 "
b11 )
b11 $
b11 (
1&
#100
0&
b111 %
b111 '
b111 *
#150
b11 !
b11 ,
b111 #
b111 +
b111 $
b111 (
1&
#200
0&
b1111 %
b1111 '
b1111 *
#250
b111 !
b111 ,
b1111 #
b1111 +
b1111 "
b1111 )
b1111 $
b1111 (
1&
#300
0&
b1010 %
b1010 '
b1010 *
#350
b1111 !
b1111 ,
b1010 #
b1010 +
b1010 $
b1010 (
1&
#400
0&
b10 %
b10 '
b10 *
#450
b1010 !
b1010 ,
b10 #
b10 +
b10 "
b10 )
b10 $
b10 (
1&
