Digital System Design/Assignments/part_1/projects_5/select8.v
//File: select8.v

`timescale 1 ns / 1 ns

module select8 (
	output reg [3:0] y,
	input [31:0] datain,
	input [2:0] sel
	
);
always @(*) begin
	case (sel)
		3'b000:		y = datain[3:0];
		3'b001:		y = datain[7:4];
		3'b010:		y = datain[11:8];
		3'b011:		y = datain[15:12];
		3'b100:		y = datain[19:16];
		3'b101:		y = datain[23:20];
		3'b110:		y = datain[27:24];
		3'b111:		y = datain[31:28];
	
		default : 	y = 4'bx;
	endcase

end

endmodule

Digital System Design/Assignments/part_1/projects_5/select8_tb.v
//File: select8_tb.v

`timescale 1 ns / 1 ns
`include "select8.v"

module select8_tb;

	wire [3:0] p_y;

	reg [31:0] p_datain;
	reg [2:0] p_sel;

	select8 m_sel8(.y(p_y),
		.datain(p_datain),
		.sel(p_sel));

	initial
	begin
		$dumpfile("select8.vcd");
		$dumpvars(0, select8_tb);

		p_datain[3:0] = 4'd0;
		p_datain[7:4] = 4'd1;
		p_datain[11:8] = 4'd2;
		p_datain[15:12] = 4'd3;
		p_datain[19:16] = 4'd4;
		p_datain[23:20] = 4'd5;
		p_datain[27:24] = 4'd6;
		p_datain[31:28] = 4'd7;
	end

	initial
	begin
		p_sel = 3'b0;

		repeat(7) begin
		#100 p_sel = p_sel + 1;
		//$display("sel = %d, y = %d.", p_sel, p_y);
		end

		#100 $stop;
	end
	initial
	begin
		$monitor("sel = %d, y = %d.", p_sel, p_y);
	end

endmodule

Digital System Design/Assignments/part_1/projects_5/select8.vcd
$date
	Sat Nov 30 20:45:53 2019
$end
$version
	Icarus Verilog
$end
$timescale
	1ns
$end
$scope module select8_tb $end
$var wire 4 ! p_y [3:0] $end
$var reg 32 " p_datain [31:0] $end
$var reg 3 # p_sel [2:0] $end
$scope module m_sel8 $end
$var wire 32 $ datain [31:0] $end
$var wire 3 % sel [2:0] $end
$var reg 4 & y [3:0] $end
$upscope $end
$upscope $end
$enddefinitions $end
#0
$dumpvars
b0 &
b0 %
b1110110010101000011001000010000 $
b0 #
b1110110010101000011001000010000 "
b0 !
$end
#100
b1 !
b1 &
b1 #
b1 %
#200
b10 !
b10 &
b10 #
b10 %
#300
b11 !
b11 &
b11 #
b11 %
#400
b100 !
b100 &
b100 #
b100 %
#500
b101 !
b101 &
b101 #
b101 %
#600
b110 !
b110 &
b110 #
b110 %
#700
b111 !
b111 &
b111 #
b111 %
