Digital System Design/Assignments/part_2/project2_F/seq_detect.v
//seq_detect.v

`timescale 1 ns / 100 ps

module seq_detect (
	output reg flag,
	input din,
	input clk,
	input rst_n
	
);
parameter	IDLE= 9'b0_0000_0001,
			A	= 9'b0_0000_0010,
			B 	= 9'b0_0000_0100,
			C 	= 9'b0_0000_1000,
			D 	= 9'b0_0001_0000,
			E 	= 9'b0_0010_0000,
			F 	= 9'b0_0100_0000,
			G 	= 9'b0_1000_0000,
			H	= 9'b1_0000_0000;

reg [8:0] state;

always @(negedge clk) begin
	if(~rst_n) begin
		flag <= 1'b0;
		state <= IDLE;
	end else begin
		case (state)
			IDLE	:	if(din) begin flag <= 1'b0; state <= A; end
						else begin flag <= 1'b0; 	state <= B; end

			A 		:	if(din) begin flag <= 1'b0; state <= C; end
						else begin flag <= 1'b0;	state <= B; end

			B 		:	if(din) begin flag <= 1'b0; state <= D; end
						else begin flag <= 1'b0;	state <= B; end

			C 		: 	if(din) begin flag <= 1'b0; state <= C; end
						else begin flag <= 1'b0; 	state <= E; end

			D 		: 	if(din) begin flag <= 1'b0; state <= F; end
						else begin flag <= 1'b0; 	state <= B; end

			E    	:	if(din) begin flag <= 1'b1; state <= G; end
						else begin flag <= 1'b0; 	state <= B; end

			F 		:	if(din) begin flag <= 1'b0; state <= C; end
						else begin flag <= 1'b1; 	state <= H; end

			G 		:	if(din) begin flag <= 1'b0; state <= F; end
						else begin flag <= 1'b0; 	state <= B; end

			H 		: 	if(din) begin flag <= 1'b1; state <= G; end
						else begin flag <= 1'b0; 	state <= B; end
		
			default : 	begin flag <= 1'b0;	state <= IDLE; end
		endcase
	end
end

endmodule

Digital System Design/Assignments/part_2/project2_F/tb_seq_detect.v
//File: tb_seq_detect.v

`timescale 1 ns / 100 ps 
`include "seq_detect.v"

module tb_seq_detect;

	wire p_flag;

	reg p_clk, p_rst, p_din;

	seq_detect seqd1(
		.flag (p_flag),
		.din  (p_din),
		.clk  (p_clk),
		.rst_n(p_rst)
		);

	initial begin 
		$dumpfile("seq_detect.vcd");
		$dumpvars(0, tb_seq_detect);

		p_rst = 1'b0;
		#25 p_rst = 1'b1;
	end

	initial begin 
		p_clk = 1'b0;
		forever begin 
			#10 p_clk = ~p_clk;
		end
	end

	parameter SIZE = 32;
	reg [SIZE - 1 : 0] data = 32'b0011_0110_1110_0001_0111_1010_0000_1101;

	initial begin : SERIES
		integer i;
		p_din = 1'b0;
		#30;
		for (i = 0; i < SIZE; i++) begin
			p_din = data[SIZE - 1];
			data = data << 1;
			#20;
		end

		$stop;
	end

	initial begin 
		#10 $display("At time %tns, reset = %b, datain = %b, flag = %b.", $time, p_rst, p_din, p_flag);
		forever begin 
			#20 $display("At time %tns, reset = %b, datain = %b, flag = %b.", $time, p_rst, p_din, p_flag);
		end
	end

endmodule

Digital System Design/Assignments/part_2/project2_F/seq_detect.vcd
$date
	Fri Dec 13 21:02:32 2019
$end
$version
	Icarus Verilog
$end
$timescale
	100ps
$end
$scope module tb_seq_detect $end
$var wire 1 ! p_flag $end
$var reg 32 " data [31:0] $end
$var reg 1 # p_clk $end
$var reg 1 $ p_din $end
$var reg 1 % p_rst $end
$scope module seqd1 $end
$var wire 1 # clk $end
$var wire 1 $ din $end
$var wire 1 % rst_n $end
$var reg 1 ! flag $end
$var reg 9 & state [8:0] $end
$upscope $end
$scope begin SERIES $end
$var integer 32 ' i [31:0] $end
$upscope $end
$upscope $end
$enddefinitions $end
#0
$dumpvars
bx '
b1 &
0%
0$
0#
b110110111000010111101000001101 "
0!
$end
#100
1#
#200
0#
#250
1%
#300
1#
b1101101110000101111010000011010 "
b0 '
#400
b100 &
0#
#500
1#
b11011011100001011110100000110100 "
b1 '
#600
0#
#700
1#
b10110111000010111101000001101000 "
1$
b10 '
#800
b10000 &
0#
#900
1#
b1101110000101111010000011010000 "
b11 '
#1000
b1000000 &
0#
#1100
1#
b11011100001011110100000110100000 "
0$
b100 '
#1200
b100000000 &
1!
0#
#1300
1#
b10111000010111101000001101000000 "
1$
b101 '
#1400
b10000000 &
0#
#1500
1#
b1110000101111010000011010000000 "
b110 '
#1600
b1000000 &
0!
0#
#1700
1#
b11100001011110100000110100000000 "
0$
b111 '
#1800
b100000000 &
1!
0#
#1900
1#
b11000010111101000001101000000000 "
1$
b1000 '
#2000
b10000000 &
0#
#2100
1#
b10000101111010000011010000000000 "
b1001 '
#2200
b1000000 &
0!
0#
#2300
1#
b1011110100000110100000000000 "
b1010 '
#2400
b1000 &
0#
#2500
1#
b10111101000001101000000000000 "
0$
b1011 '
#2600
b100000 &
0#
#2700
1#
b101111010000011010000000000000 "
b1100 '
#2800
b100 &
0#
#2900
1#
b1011110100000110100000000000000 "
b1101 '
#3000
0#
#3100
1#
b10111101000001101000000000000000 "
b1110 '
#3200
0#
#3300
1#
b1111010000011010000000000000000 "
1$
b1111 '
#3400
b10000 &
0#
#3500
1#
b11110100000110100000000000000000 "
0$
b10000 '
#3600
b100 &
0#
#3700
1#
b11101000001101000000000000000000 "
1$
b10001 '
#3800
b10000 &
0#
#3900
1#
b11010000011010000000000000000000 "
b10010 '
#4000
b1000000 &
0#
#4100
1#
b10100000110100000000000000000000 "
b10011 '
#4200
b1000 &
0#
#4300
1#
b1000001101000000000000000000000 "
b10100 '
#4400
0#
#4500
1#
b10000011010000000000000000000000 "
0$
b10101 '
#4600
b100000 &
0#
#4700
1#
b110100000000000000000000000 "
1$
b10110 '
#4800
b10000000 &
1!
0#
#4900
1#
b1101000000000000000000000000 "
0$
b10111 '
#5000
b100 &
0!
0#
#5100
1#
b11010000000000000000000000000 "
b11000 '
#5200
0#
#5300
1#
b110100000000000000000000000000 "
b11001 '
#5400
0#
#5500
1#
b1101000000000000000000000000000 "
b11010 '
#5600
0#
#5700
1#
b11010000000000000000000000000000 "
b11011 '
#5800
0#
#5900
1#
b10100000000000000000000000000000 "
1$
b11100 '
#6000
b10000 &
0#
#6100
1#
b1000000000000000000000000000000 "
b11101 '
#6200
b1000000 &
0#
#6300
1#
b10000000000000000000000000000000 "
0$
b11110 '
#6400
b100000000 &
1!
0#
#6500
1#
b0 "
1$
b11111 '
#6600
b10000000 &
0#
