Digital System Design/Assignments/part_1/projects_1/compare8b.v
//File: compare8b.v
`timescale 10 ns / 1 ns

module compare8b (
	output y,
	input [7:0] a,
	input [7:0] b

);

assign y = (a > b) ? 1 : 0;

endmodule

Digital System Design/Assignments/part_1/projects_1/compare8b_tb.v
//File: compare8b_tb.v
`timescale 10 ns / 1 ns
`include "compare8b.v"

module compare8b_tb;
	wire p_y;
	reg [7:0] p_a, p_b;

	compare8b tb_cmp8b(.y(p_y), .a(p_a), .b(p_b));

	initial
	begin
		$dumpfile("compare8b.vcd");
		$dumpvars(0, compare8b_tb);
		p_a = 0; p_b = 0;
		repeat(255)
		begin
			#1 p_a = p_a + 1;
			p_b = 0;
			repeat(255)
			begin
				#1 p_b = p_b + 1;
			end
		end
		#5 $stop;
	end

	initial
	begin
		$monitor("当前时间: %tns,",$time,"<---->y=%b, a=%b, b=%b",p_y,p_a,p_b);
	end

endmodule

Digital System Design/Assignments/part_1/projects_1/compare8b.vcd
$date
	Sat Nov 30 01:10:05 2019
$end
$version
	Icarus Verilog
$end
$timescale
	1ns
$end
$scope module compare8b_tb $end
$var wire 1 ! p_y $end
$var reg 8 " p_a [7:0] $end
$var reg 8 # p_b [7:0] $end
$scope module tb_cmp8b $end
$var wire 8 $ a [7:0] $end
$var wire 8 % b [7:0] $end
$var wire 1 ! y $end
$upscope $end
$upscope $end
$enddefinitions $end
#0
$dumpvars
b0 %
b0 $
b0 #
b0 "
0!
$end
#10
1!
b1 "
b1 $
#20
0!
b1 #
b1 %
#30
b10 #
b10 %
#40
b11 #
b11 %
#50
b100 #
b100 %
#60
b101 #
b101 %
#70
b110 #
b110 %
#80
b111 #
b111 %
#90
b1000 #
b1000 %
#100
b1001 #
b1001 %
#110
b1010 #
b1010 %
#120
b1011 #
b1011 %
#130
b1100 #
b1100 %
#140
b1101 #
b1101 %
#150
b1110 #
b1110 %
#160
b1111 #
b1111 %
#170
b10000 #
b10000 %
#180
b10001 #
b10001 %
#190
b10010 #
b10010 %
#200
b10011 #
b10011 %
#210
b10100 #
b10100 %
#220
b10101 #
b10101 %
#230
b10110 #
b10110 %
#240
b10111 #
b10111 %
#250
b11000 #
b11000 %
#260
b11001 #
b11001 %
#270
b11010 #
b11010 %
#280
b11011 #
b11011 %
#290
b11100 #
b11100 %
#300
b11101 #
b11101 %
#310
b11110 #
b11110 %
#320
b11111 #
b11111 %
#330
b100000 #
b100000 %
#340
b100001 #
b100001 %
#350
b100010 #
b100010 %
#360
b100011 #
b100011 %
#370
b100100 #
b100100 %
#380
b100101 #
b100101 %
#390
b100110 #
b100110 %
#400
b100111 #
b100111 %
#410
b101000 #
b101000 %
#420
b101001 #
b101001 %
#430
b101010 #
b101010 %
#440
b101011 #
b101011 %
#450
b101100 #
b101100 %
#460
b101101 #
b101101 %
#470
b101110 #
b101110 %
#480
b101111 #
b101111 %
#490
b110000 #
b110000 %
#500
b110001 #
b110001 %
#510
b110010 #
b110010 %
#520
b110011 #
b110011 %
#530
b110100 #
b110100 %
#540
b110101 #
b110101 %
#550
b110110 #
b110110 %
#560
b110111 #
b110111 %
#570
b111000 #
b111000 %
#580
b111001 #
b111001 %
#590
b111010 #
b111010 %
#600
b111011 #
b111011 %
#610
b111100 #
b111100 %
#620
b111101 #
b111101 %
#630
b111110 #
b111110 %
#640
b111111 #
b111111 %
#650
b1000000 #
b1000000 %
#660
b1000001 #
b1000001 %
#670
b1000010 #
b1000010 %
#680
b1000011 #
b1000011 %
#690
b1000100 #
b1000100 %
#700
b1000101 #
b1000101 %
#710
b1000110 #
b1000110 %
#720
b1000111 #
b1000111 %
#730
b1001000 #
b1001000 %
#740
b1001001 #
b1001001 %
#750
b1001010 #
b1001010 %
#760
b1001011 #
b1001011 %
#770
b1001100 #
b1001100 %
#780
b1001101 #
b1001101 %
#790
b1001110 #
b1001110 %
#800
b1001111 #
b1001111 %
#810
b1010000 #
b1010000 %
#820
b1010001 #
b1010001 %
#830
b1010010 #
b1010010 %
#840
b1010011 #
b1010011 %
#850
b1010100 #
b1010100 %
#860
b1010101 #
b1010101 %
#870
b1010110 #
b1010110 %
#880
b1010111 #
b1010111 %
#890
b1011000 #
b1011000 %
#900
b1011001 #
b1011001 %
#910
b1011010 #
b1011010 %
#920
b1011011 #
b1011011 %
#930
b1011100 #
b1011100 %
#940
b1011101 #
b1011101 %
#950
b1011110 #
b1011110 %
#960
b1011111 #
b1011111 %
#970
b1100000 #
b1100000 %
#980
b1100001 #
b1100001 %
#990
b1100010 #
b1100010 %
#1000
b1100011 #
b1100011 %
#1010
b1100100 #
b1100100 %
#1020
b1100101 #
b1100101 %
#1030
b1100110 #
b1100110 %
#1040
b1100111 #
b1100111 %
#1050
b1101000 #
b1101000 %
#1060
b1101001 #
b1101001 %
#1070
b1101010 #
b1101010 %
#1080
b1101011 #
b1101011 %
#1090
b1101100 #
b1101100 %
#1100
b1101101 #
b1101101 %
#1110
b1101110 #
b1101110 %
#1120
b1101111 #
b1101111 %
#1130
b1110000 #
b1110000 %
#1140
b1110001 #
b1110001 %
#1150
b1110010 #
b1110010 %
#1160
b1110011 #
b1110011 %
#1170
b1110100 #
b1110100 %
#1180
b1110101 #
b1110101 %
#1190
b1110110 #
b1110110 %
#1200
b1110111 #
b1110111 %
#1210
b1111000 #
b1111000 %
#1220
b1111001 #
b1111001 %
#1230
b1111010 #
b1111010 %
#1240
b1111011 #
b1111011 %
#1250
b1111100 #
b1111100 %
#1260
b1111101 #
b1111101 %
#1270
b1111110 #
b1111110 %
#1280
b1111111 #
b1111111 %
#1290
b10000000 #
b10000000 %
#1300
b10000001 #
b10000001 %
#1310
b10000010 #
b10000010 %
#1320
b10000011 #
b10000011 %
#1330
b10000100 #
b10000100 %
#1340
b10000101 #
b10000101 %
#1350
b10000110 #
b10000110 %
#1360
b10000111 #
b10000111 %
#1370
b10001000 #
b10001000 %
#1380
b10001001 #
b10001001 %
#1390
b10001010 #
b10001010 %
#1400
b10001011 #
b10001011 %
#1410
b10001100 #
b10001100 %
#1420
b10001101 #
b10001101 %
#1430
b10001110 #
b10001110 %
#1440
b10001111 #
b10001111 %
#1450
b10010000 #
b10010000 %
#1460
b10010001 #
b10010001 %
#1470
b10010010 #
b10010010 %
#1480
b10010011 #
b10010011 %
#1490
b10010100 #
b10010100 %
#1500
b10010101 #
b10010101 %
#1510
b10010110 #
b10010110 %
#1520
b10010111 #
b10010111 %
#1530
b10011000 #
b10011000 %
#1540
b10011001 #
b10011001 %
#1550
b10011010 #
b10011010 %
#1560
b10011011 #
b10011011 %
#1570
b10011100 #
b10011100 %
#1580
b10011101 #
b10011101 %
#1590
b10011110 #
b10011110 %
#1600
b10011111 #
b10011111 %
#1610
b10100000 #
b10100000 %
#1620
b10100001 #
b10100001 %
#1630
b10100010 #
b10100010 %
#1640
b10100011 #
b10100011 %
#1650
b10100100 #
b10100100 %
#1660
b10100101 #
b10100101 %
#1670
b10100110 #
b10100110 %
#1680
b10100111 #
b10100111 %
#1690
b10101000 #
b10101000 %
#1700
b10101001 #
b10101001 %
#1710
b10101010 #
b10101010 %
#1720
b10101011 #
b10101011 %
#1730
b10101100 #
b10101100 %
#1740
b10101101 #
b10101101 %
#1750
b10101110 #
b10101110 %
#1760
b10101111 #
b10101111 %
#1770
b10110000 #
b10110000 %
#1780
b10110001 #
b10110001 %
#1790
b10110010 #
b10110010 %
#1800
b10110011 #
b10110011 %
#1810
b10110100 #
b10110100 %
#1820
b10110101 #
b10110101 %
#1830
b10110110 #
b10110110 %
#1840
b10110111 #
b10110111 %
#1850
b10111000 #
b10111000 %
#1860
b10111001 #
b10111001 %
#1870
b10111010 #
b10111010 %
#1880
b10111011 #
b10111011 %
#1890
b10111100 #
b10111100 %
#1900
b10111101 #
b10111101 %
#1910
b10111110 #
b10111110 %
#1920
b10111111 #
b10111111 %
#1930
b11000000 #
b11000000 %
#1940
b11000001 #
b11000001 %
#1950
b11000010 #
b11000010 %
#1960
b11000011 #
b11000011 %
#1970
b11000100 #
b11000100 %
#1980
b11000101 #
b11000101 %
#1990
b11000110 #
b11000110 %
#2000
b11000111 #
b11000111 %
#2010
b11001000 #
b11001000 %
#2020
b11001001 #
b11001001 %
#2030
b11001010 #
b11001010 %
#2040
b11001011 #
b11001011 %
#2050
b11001100 #
b11001100 %
#2060
b11001101 #
b11001101 %
#2070
b11001110 #
b11001110 %
#2080
b11001111 #
b11001111 %
#2090
b11010000 #
b11010000 %
#2100
b11010001 #
b11010001 %
#2110
b11010010 #
b11010010 %
#2120
b11010011 #
b11010011 %
#2130
b11010100 #
b11010100 %
#2140
b11010101 #
b11010101 %
#2150
b11010110 #
b11010110 %
#2160
b11010111 #
b11010111 %
#2170
b11011000 #
b11011000 %
#2180
b11011001 #
b11011001 %
#2190
b11011010 #
b11011010 %
#2200
b11011011 #
b11011011 %
#2210
b11011100 #
b11011100 %
#2220
b11011101 #
b11011101 %
#2230
b11011110 #
b11011110 %
#2240
b11011111 #
b11011111 %
#2250
b11100000 #
b11100000 %
#2260
b11100001 #
b11100001 %
#2270
b11100010 #
b11100010 %
#2280
b11100011 #
b11100011 %
#2290
b11100100 #
b11100100 %
#2300
b11100101 #
b11100101 %
#2310
b11100110 #
b11100110 %
#2320
b11100111 #
b11100111 %
#2330
b11101000 #
b11101000 %
#2340
b11101001 #
b11101001 %
#2350
b11101010 #
b11101010 %
#2360
b11101011 #
b11101011 %
#2370
b11101100 #
b11101100 %
#2380
b11101101 #
b11101101 %
#2390
b11101110 #
b11101110 %
#2400
b11101111 #
b11101111 %
#2410
b11110000 #
b11110000 %
#2420
b11110001 #
b11110001 %
#2430
b11110010 #
b11110010 %
#2440
b11110011 #
b11110011 %
#2450
b11110100 #
b11110100 %
#2460
b11110101 #
b11110101 %
#2470
b11110110 #
b11110110 %
#2480
b11110111 #
b11110111 %
#2490
b11111000 #
b11111000 %
#2500
b11111001 #
b11111001 %
#2510
b11111010 #
b11111010 %
#2520
b11111011 #
b11111011 %
#2530
b11111100 #
b11111100 %
#2540
b11111101 #
b11111101 %
#2550
b11111110 #
b11111110 %
#2560
b11111111 #
b11111111 %
#2570
1!
b0 #
b0 %
b10 "
b10 $
#2580
b1 #
b1 %
#2590
0!
b10 #
b10 %
#2600
b11 #
b11 %
#2610
b100 #
b100 %
#2620
b101 #
b101 %
#2630
b110 #
b110 %
#2640
b111 #
b111 %
#2650
b1000 #
b1000 %
#2660
b1001 #
b1001 %
#2670
b1010 #
b1010 %
#2680
b1011 #
b1011 %
#2690
b1100 #
b1100 %
#2700
b1101 #
b1101 %
#2710
b1110 #
b1110 %
#2720
b1111 #
b1111 %
#2730
b10000 #
b10000 %
#2740
b10001 #
b10001 %
#2750
b10010 #
b10010 %
#2760
b10011 #
b10011 %
#2770
b10100 #
b10100 %
#2780
b10101 #
b10101 %
#2790
b10110 #
b10110 %
#2800
b10111 #
b10111 %
#2810
b11000 #
b11000 %
#2820
b11001 #
b11001 %
#2830
b11010 #
b11010 %
#2840
b11011 #
b11011 %
#2850
b11100 #
b11100 %
#2860
b11101 #
b11101 %
#2870
b11110 #
b11110 %
#2880
b11111 #
b11111 %
#2890
b100000 #
b100000 %
#2900
b100001 #
b100001 %
#2910
b100010 #
b100010 %
#2920
b100011 #
b100011 %
#2930
b100100 #
b100100 %
#2940
b100101 #
b100101 %
#2950
b100110 #
b100110 %
#2960
b100111 #
b100111 %
#2970
b101000 #
b101000 %
#2980
b101001 #
b101001 %
#2990
b101010 #
b101010 %
#3000
b101011 #
b101011 %
#3010
b101100 #
b101100 %
#3020
b101101 #
b101101 %
#3030
b101110 #
b101110 %
#3040
b101111 #
b101111 %
#3050
b110000 #
b110000 %
#3060
b110001 #
b110001 %
#3070
b110010 #
b110010 %
#3080
b110011 #
b110011 %
#3090
b110100 #
b110100 %
#3100
b110101 #
b110101 %
#3110
b110110 #
b110110 %
#3120
b110111 #
b110111 %
#3130
b111000 #
b111000 %
#3140
b111001 #
b111001 %
#3150
b111010 #
b111010 %
#3160
b111011 #
b111011 %
#3170
b111100 #
b111100 %
#3180
b111101 #
b111101 %
#3190
b111110 #
b111110 %
#3200
b111111 #
b111111 %
#3210
b1000000 #
b1000000 %
#3220
b1000001 #
b1000001 %
#3230
b1000010 #
b1000010 %
#3240
b1000011 #
b1000011 %
#3250
b1000100 #
b1000100 %
#3260
b1000101 #
b1000101 %
#3270
b1000110 #
b1000110 %
#3280
b1000111 #
b1000111 %
#3290
b1001000 #
b1001000 %
#3300
b1001001 #
b1001001 %
#3310
b1001010 #
b1001010 %
#3320
b1001011 #
b1001011 %
#3330
b1001100 #
b1001100 %
#3340
b1001101 #
b1001101 %
#3350
b1001110 #
b1001110 %
#3360
b1001111 #
b1001111 %
#3370
b1010000 #
b1010000 %
#3380
b1010001 #
b1010001 %
#3390
b1010010 #
b1010010 %
#3400
b1010011 #
b1010011 %
#3410
b1010100 #
b1010100 %
#3420
b1010101 #
b1010101 %
#3430
b1010110 #
b1010110 %
#3440
b1010111 #
b1010111 %
#3450
b1011000 #
b1011000 %
#3460
b1011001 #
b1011001 %
#3470
b1011010 #
b1011010 %
#3480
b1011011 #
b1011011 %
#3490
b1011100 #
b1011100 %
#3500
b1011101 #
b1011101 %
#3510
b1011110 #
b1011110 %
#3520
b1011111 #
b1011111 %
#3530
b1100000 #
b1100000 %
#3540
b1100001 #
b1100001 %
#3550
b1100010 #
b1100010 %
#3560
b1100011 #
b1100011 %
#3570
b1100100 #
b1100100 %
#3580
b1100101 #
b1100101 %
#3590
b1100110 #
b1100110 %
#3600
b1100111 #
b1100111 %
#3610
b1101000 #
b1101000 %
#3620
b1101001 #
b1101001 %
#3630
b1101010 #
b1101010 %
#3640
b1101011 #
b1101011 %
#3650
b1101100 #
b1101100 %
#3660
b1101101 #
b1101101 %
#3670
b1101110 #
b1101110 %
#3680
b1101111 #
b1101111 %
#3690
b1110000 #
b1110000 %
#3700
b1110001 #
b1110001 %
#3710
b1110010 #
b1110010 %
#3720
b1110011 #
b1110011 %
#3730
b1110100 #
b1110100 %
#3740
b1110101 #
b1110101 %
#3750
b1110110 #
b1110110 %
#3760
b1110111 #
b1110111 %
#3770
b1111000 #
b1111000 %
#3780
b1111001 #
b1111001 %
#3790
b1111010 #
b1111010 %
#3800
b1111011 #
b1111011 %
#3810
b1111100 #
b1111100 %
#3820
b1111101 #
b1111101 %
#3830
b1111110 #
b1111110 %
#3840
b1111111 #
b1111111 %
#3850
b10000000 #
b10000000 %
#3860
b10000001 #
b10000001 %
#3870
b10000010 #
b10000010 %
#3880
b10000011 #
b10000011 %
#3890
b10000100 #
b10000100 %
#3900
b10000101 #
b10000101 %
#3910
b10000110 #
b10000110 %
#3920
b10000111 #
b10000111 %
#3930
b10001000 #
b10001000 %
#3940
b10001001 #
b10001001 %
#3950
b10001010 #
b10001010 %
#3960
b10001011 #
b10001011 %
#3970
b10001100 #
b10001100 %
#3980
b10001101 #
b10001101 %
#3990
b10001110 #
b10001110 %
#4000
b10001111 #
b10001111 %
#4010
b10010000 #
b10010000 %
#4020
b10010001 #
b10010001 %
#4030
b10010010 #
b10010010 %
#4040
b10010011 #
b10010011 %
#4050
b10010100 #
b10010100 %
#4060
b10010101 #
b10010101 %
#4070
b10010110 #
b10010110 %
#4080
b10010111 #
b10010111 %
#4090
b10011000 #
b10011000 %
#4100
b10011001 #
b10011001 %
#4110
b10011010 #
b10011010 %
#4120
b10011011 #
b10011011 %
#4130
b10011100 #
b10011100 %
#4140
b10011101 #
b10011101 %
#4150
b10011110 #
b10011110 %
#4160
b10011111 #
b10011111 %
#4170
b10100000 #
b10100000 %
#4180
b10100001 #
b10100001 %
#4190
b10100010 #
b10100010 %
#4200
b10100011 #
b10100011 %
#4210
b10100100 #
b10100100 %
#4220
b10100101 #
b10100101 %
#4230
b10100110 #
b10100110 %
#4240
b10100111 #
b10100111 %
#4250
b10101000 #
b10101000 %
#4260
b10101001 #
b10101001 %
#4270
b10101010 #
b10101010 %
#4280
b10101011 #
b10101011 %
#4290
b10101100 #
b10101100 %
#4300
b10101101 #
b10101101 %
#4310
b10101110 #
b10101110 %
#4320
b10101111 #
b10101111 %
#4330
b10110000 #
b10110000 %
#4340
b10110001 #
b10110001 %
#4350
b10110010 #
b10110010 %
#4360
b10110011 #
b10110011 %
#4370
b10110100 #
b10110100 %
#4380
b10110101 #
b10110101 %
#4390
b10110110 #
b10110110 %
#4400
b10110111 #
b10110111 %
#4410
b10111000 #
b10111000 %
#4420
b10111001 #
b10111001 %
#4430
b10111010 #
b10111010 %
#4440
b10111011 #
b10111011 %
#4450
b10111100 #
b10111100 %
#4460
b10111101 #
b10111101 %
#4470
b10111110 #
b10111110 %
#4480
b10111111 #
b10111111 %
#4490
b11000000 #
b11000000 %
#4500
b11000001 #
b11000001 %
#4510
b11000010 #
b11000010 %
#4520
b11000011 #
b11000011 %
#4530
b11000100 #
b11000100 %
#4540
b11000101 #
b11000101 %
#4550
b11000110 #
b11000110 %
#4560
b11000111 #
b11000111 %
#4570
b11001000 #
b11001000 %
#4580
b11001001 #
b11001001 %
#4590
b11001010 #
b11001010 %
#4600
b11001011 #
b11001011 %
#4610
b11001100 #
b11001100 %
#4620
b11001101 #
b11001101 %
#4630
b11001110 #
b11001110 %
#4640
b11001111 #
b11001111 %
#4650
b11010000 #
b11010000 %
#4660
b11010001 #
b11010001 %
#4670
b11010010 #
b11010010 %
#4680
b11010011 #
b11010011 %
#4690
b11010100 #
b11010100 %
#4700
b11010101 #
b11010101 %
#4710
b11010110 #
b11010110 %
#4720
b11010111 #
b11010111 %
#4730
b11011000 #
b11011000 %
#4740
b11011001 #
b11011001 %
#4750
b11011010 #
b11011010 %
#4760
b11011011 #
b11011011 %
#4770
b11011100 #
b11011100 %
#4780
b11011101 #
b11011101 %
#4790
b11011110 #
b11011110 %
#4800
b11011111 #
b11011111 %
#4810
b11100000 #
b11100000 %
#4820
b11100001 #
b11100001 %
#4830
b11100010 #
b11100010 %
#4840
b11100011 #
b11100011 %
#4850
b11100100 #
b11100100 %
#4860
b11100101 #
b11100101 %
#4870
b11100110 #
b11100110 %
#4880
b11100111 #
b11100111 %
#4890
b11101000 #
b11101000 %
#4900
b11101001 #
b11101001 %
#4910
b11101010 #
b11101010 %
#4920
b11101011 #
b11101011 %
#4930
b11101100 #
b11101100 %
#4940
b11101101 #
b11101101 %
#4950
b11101110 #
b11101110 %
#4960
b11101111 #
b11101111 %
#4970
b11110000 #
b11110000 %
#4980
b11110001 #
b11110001 %
#4990
b11110010 #
b11110010 %
#5000
b11110011 #
b11110011 %
#5010
b11110100 #
b11110100 %
#5020
b11110101 #
b11110101 %
#5030
b11110110 #
b11110110 %
#5040
b11110111 #
b11110111 %
#5050
b11111000 #
b11111000 %
#5060
b11111001 #
b11111001 %
#5070
b11111010 #
b11111010 %
#5080
b11111011 #
b11111011 %
#5090
b11111100 #
b11111100 %
#5100
b11111101 #
b11111101 %
#5110
b11111110 #
b11111110 %
#5120
b11111111 #
b11111111 %
#5130
1!
b0 #
b0 %
b11 "
b11 $
#5140
b1 #
b1 %
#5150
b10 #
b10 %
#5160
0!
b11 #
b11 %
#5170
b100 #
b100 %
#5180
b101 #
b101 %
#5190
b110 #
b110 %
#5200
b111 #
b111 %
#5210
b1000 #
b1000 %
#5220
b1001 #
b1001 %
#5230
b1010 #
b1010 %
#5240
b1011 #
b1011 %
#5250
b1100 #
b1100 %
#5260
b1101 #
b1101 %
#5270
b1110 #
b1110 %
#5280
b1111 #
b1111 %
#5290
b10000 #
b10000 %
#5300
b10001 #
b10001 %
#5310
b10010 #
b10010 %
#5320
b10011 #
b10011 %
#5330
b10100 #
b10100 %
#5340
b10101 #
b10101 %
#5350
b10110 #
b10110 %
#5360
b10111 #
b10111 %
#5370
b11000 #
b11000 %
#5380
b11001 #
b11001 %
#5390
b11010 #
b11010 %
#5400
b11011 #
b11011 %
#5410
b11100 #
b11100 %
#5420
b11101 #
b11101 %
#5430
b11110 #
b11110 %
#5440
b11111 #
b11111 %
#5450
b100000 #
b100000 %
#5460
b100001 #
b100001 %
#5470
b100010 #
b100010 %
#5480
b100011 #
b100011 %
#5490
b100100 #
b100100 %
#5500
b100101 #
b100101 %
#5510
b100110 #
b100110 %
#5520
b100111 #
b100111 %
#5530
b101000 #
b101000 %
#5540
b101001 #
b101001 %
#5550
b101010 #
b101010 %
#5560
b101011 #
b101011 %
#5570
b101100 #
b101100 %
#5580
b101101 #
b101101 %
#5590
b101110 #
b101110 %
#5600
b101111 #
b101111 %
#5610
b110000 #
b110000 %
#5620
b110001 #
b110001 %
#5630
b110010 #
b110010 %
#5640
b110011 #
b110011 %
#5650
b110100 #
b110100 %
#5660
b110101 #
b110101 %
#5670
b110110 #
b110110 %
#5680
b110111 #
b110111 %
#5690
b111000 #
b111000 %
#5700
b111001 #
b111001 %
#5710
b111010 #
b111010 %
#5720
b111011 #
b111011 %
#5730
b111100 #
b111100 %
#5740
b111101 #
b111101 %
#5750
b111110 #
b111110 %
#5760
b111111 #
b111111 %
#5770
b1000000 #
b1000000 %
#5780
b1000001 #
b1000001 %
#5790
b1000010 #
b1000010 %
#5800
b1000011 #
b1000011 %
#5810
b1000100 #
b1000100 %
#5820
b1000101 #
b1000101 %
#5830
b1000110 #
b1000110 %
#5840
b1000111 #
b1000111 %
#5850
b1001000 #
b1001000 %
#5860
b1001001 #
b1001001 %
#5870
b1001010 #
b1001010 %
#5880
b1001011 #
b1001011 %
#5890
b1001100 #
b1001100 %
#5900
b1001101 #
b1001101 %
#5910
b1001110 #
b1001110 %
#5920
b1001111 #
b1001111 %
#5930
b1010000 #
b1010000 %
#5940
b1010001 #
b1010001 %
#5950
b1010010 #
b1010010 %
#5960
b1010011 #
b1010011 %
#5970
b1010100 #
b1010100 %
#5980
b1010101 #
b1010101 %
#5990
b1010110 #
b1010110 %
#6000
b1010111 #
b1010111 %
#6010
b1011000 #
b1011000 %
#6020
b1011001 #
b1011001 %
#6030
b1011010 #
b1011010 %
#6040
b1011011 #
b1011011 %
#6050
b1011100 #
b1011100 %
#6060
b1011101 #
b1011101 %
#6070
b1011110 #
b1011110 %
#6080
b1011111 #
b1011111 %
#6090
b1100000 #
b1100000 %
#6100
b1100001 #
b1100001 %
#6110
b1100010 #
b1100010 %
#6120
b1100011 #
b1100011 %
#6130
b1100100 #
b1100100 %
#6140
b1100101 #
b1100101 %
#6150
b1100110 #
b1100110 %
#6160
b1100111 #
b1100111 %
#6170
b1101000 #
b1101000 %
#6180
b1101001 #
b1101001 %
#6190
b1101010 #
b1101010 %
#6200
b1101011 #
b1101011 %
#6210
b1101100 #
b1101100 %
#6220
b1101101 #
b1101101 %
#6230
b1101110 #
b1101110 %
#6240
b1101111 #
b1101111 %
#6250
b1110000 #
b1110000 %
#6260
b1110001 #
b1110001 %
#6270
b1110010 #
b1110010 %
#6280
b1110011 #
b1110011 %
#6290
b1110100 #
b1110100 %
#6300
b1110101 #
b1110101 %
#6310
b1110110 #
b1110110 %
#6320
b1110111 #
b1110111 %
#6330
b1111000 #
b1111000 %
#6340
b1111001 #
b1111001 %
#6350
b1111010 #
b1111010 %
#6360
b1111011 #
b1111011 %
#6370
b1111100 #
b1111100 %
#6380
b1111101 #
b1111101 %
#6390
b1111110 #
b1111110 %
#6400
b1111111 #
b1111111 %
#6410
b10000000 #
b10000000 %
#6420
b10000001 #
b10000001 %
#6430
b10000010 #
b10000010 %
#6440
b10000011 #
b10000011 %
#6450
b10000100 #
b10000100 %
#6460
b10000101 #
b10000101 %
#6470
b10000110 #
b10000110 %
#6480
b10000111 #
b10000111 %
#6490
b10001000 #
b10001000 %
#6500
b10001001 #
b10001001 %
#6510
b10001010 #
b10001010 %
#6520
b10001011 #
b10001011 %
#6530
b10001100 #
b10001100 %
#6540
b10001101 #
b10001101 %
#6550
b10001110 #
b10001110 %
#6560
b10001111 #
b10001111 %
#6570
b10010000 #
b10010000 %
#6580
b10010001 #
b10010001 %
#6590
b10010010 #
b10010010 %
#6600
b10010011 #
b10010011 %
#6610
b10010100 #
b10010100 %
#6620
b10010101 #
b10010101 %
#6630
b10010110 #
b10010110 %
#6640
b10010111 #
b10010111 %
#6650
b10011000 #
b10011000 %
#6660
b10011001 #
b10011001 %
#6670
b10011010 #
b10011010 %
#6680
b10011011 #
b10011011 %
#6690
b10011100 #
b10011100 %
#6700
b10011101 #
b10011101 %
#6710
b10011110 #
b10011110 %
#6720
b10011111 #
b10011111 %
#6730
b10100000 #
b10100000 %
#6740
b10100001 #
b10100001 %
#6750
b10100010 #
b10100010 %
#6760
b10100011 #
b10100011 %
#6770
b10100100 #
b10100100 %
#6780
b10100101 #
b10100101 %
#6790
b10100110 #
b10100110 %
#6800
b10100111 #
b10100111 %
#6810
b10101000 #
b10101000 %
#6820
b10101001 #
b10101001 %
#6830
b10101010 #
b10101010 %
#6840
b10101011 #
b10101011 %
#6850
b10101100 #
b10101100 %
#6860
b10101101 #
b10101101 %
#6870
b10101110 #
b10101110 %
#6880
b10101111 #
b10101111 %
#6890
b10110000 #
b10110000 %
#6900
b10110001 #
b10110001 %
#6910
b10110010 #
b10110010 %
#6920
b10110011 #
b10110011 %
#6930
b10110100 #
b10110100 %
#6940
b10110101 #
b10110101 %
#6950
b10110110 #
b10110110 %
#6960
b10110111 #
b10110111 %
#6970
b10111000 #
b10111000 %
#6980
b10111001 #
b10111001 %
#6990
b10111010 #
b10111010 %
#7000
b10111011 #
b10111011 %
#7010
b10111100 #
b10111100 %
#7020
b10111101 #
b10111101 %
#7030
b10111110 #
b10111110 %
#7040
b10111111 #
b10111111 %
#7050
b11000000 #
b11000000 %
#7060
b11000001 #
b11000001 %
#7070
b11000010 #
b11000010 %
#7080
b11000011 #
b11000011 %
#7090
b11000100 #
b11000100 %
#7100
b11000101 #
b11000101 %
#7110
b11000110 #
b11000110 %
#7120
b11000111 #
b11000111 %
#7130
b11001000 #
b11001000 %
#7140
b11001001 #
b11001001 %
#7150
b11001010 #
b11001010 %
#7160
b11001011 #
b11001011 %
#7170
b11001100 #
b11001100 %
#7180
b11001101 #
b11001101 %
#7190
b11001110 #
b11001110 %
#7200
b11001111 #
b11001111 %
#7210
b11010000 #
b11010000 %
#7220
b11010001 #
b11010001 %
#7230
b11010010 #
b11010010 %
#7240
b11010011 #
b11010011 %
#7250
b11010100 #
b11010100 %
#7260
b11010101 #
b11010101 %
#7270
b11010110 #
b11010110 %
#7280
b11010111 #
b11010111 %
#7290
b11011000 #
b11011000 %
#7300
b11011001 #
b11011001 %
#7310
b11011010 #
b11011010 %
#7320
b11011011 #
b11011011 %
#7330
b11011100 #
b11011100 %
#7340
b11011101 #
b11011101 %
#7350
b11011110 #
b11011110 %
#7360
b11011111 #
b11011111 %
#7370
b11100000 #
b11100000 %
#7380
b11100001 #
b11100001 %
#7390
b11100010 #
b11100010 %
#7400
b11100011 #
b11100011 %
#7410
b11100100 #
b11100100 %
#7420
b11100101 #
b11100101 %
#7430
b11100110 #
b11100110 %
#7440
b11100111 #
b11100111 %
#7450
b11101000 #
b11101000 %
#7460
b11101001 #
b11101001 %
#7470
b11101010 #
b11101010 %
#7480
b11101011 #
b11101011 %
#7490
b11101100 #
b11101100 %
#7500
b11101101 #
b11101101 %
#7510
b11101110 #
b11101110 %
#7520
b11101111 #
b11101111 %
#7530
b11110000 #
b11110000 %
#7540
b11110001 #
b11110001 %
#7550
b11110010 #
b11110010 %
#7560
b11110011 #
b11110011 %
#7570
b11110100 #
b11110100 %
#7580
b11110101 #
b11110101 %
#7590
b11110110 #
b11110110 %
#7600
b11110111 #
b11110111 %
#7610
b11111000 #
b11111000 %
#7620
b11111001 #
b11111001 %
#7630
b11111010 #
b11111010 %
#7640
b11111011 #
b11111011 %
#7650
b11111100 #
b11111100 %
#7660
b11111101 #
b11111101 %
#7670
b11111110 #
b11111110 %
#7680
b11111111 #
b11111111 %
#7690
1!
b0 #
b0 %
b100 "
b100 $
#7700
b1 #
b1 %
#7710
b10 #
b10 %
#7720
b11 #
b11 %
#7730
0!
b100 #
b100 %
#7740
b101 #
b101 %
#7750
b110 #
b110 %
#7760
b111 #
b111 %
#7770
b1000 #
b1000 %
#7780
b1001 #
b1001 %
#7790
b1010 #
b1010 %
#7800
b1011 #
b1011 %
#7810
b1100 #
b1100 %
#7820
b1101 #
b1101 %
#7830
b1110 #
b1110 %
#7840
b1111 #
b1111 %
#7850
b10000 #
b10000 %
#7860
b10001 #
b10001 %
#7870
b10010 #
b10010 %
#7880
b10011 #
b10011 %
#7890
b10100 #
b10100 %
#7900
b10101 #
b10101 %
#7910
b10110 #
b10110 %
#7920
b10111 #
b10111 %
#7930
b11000 #
b11000 %
#7940
b11001 #
b11001 %
#7950
b11010 #
b11010 %
#7960
b11011 #
b11011 %
#7970
b11100 #
b11100 %
#7980
b11101 #
b11101 %
#7990
b11110 #
b11110 %
#8000
b11111 #
b11111 %
#8010
b100000 #
b100000 %
#8020
b100001 #
b100001 %
#8030
b100010 #
b100010 %
#8040
b100011 #
b100011 %
#8050
b100100 #
b100100 %
#8060
b100101 #
b100101 %
#8070
b100110 #
b100110 %
#8080
b100111 #
b100111 %
#8090
b101000 #
b101000 %
#8100
b101001 #
b101001 %
#8110
b101010 #
b101010 %
#8120
b101011 #
b101011 %
#8130
b101100 #
b101100 %
#8140
b101101 #
b101101 %
#8150
b101110 #
b101110 %
#8160
b101111 #
b101111 %
#8170
b110000 #
b110000 %
#8180
b110001 #
b110001 %
#8190
b110010 #
b110010 %
#8200
b110011 #
b110011 %
#8210
b110100 #
b110100 %
#8220
b110101 #
b110101 %
#8230
b110110 #
b110110 %
#8240
b110111 #
b110111 %
#8250
b111000 #
b111000 %
#8260
b111001 #
b111001 %
