Digital System Design/Assignments/part_2/project2_C/ALU.v
//File: ALU.v

`timescale 1 ns / 1 ns

`define OP_AND		4'd0
`define OP_SUBSTR	4'd1
`define OP_SUBSTR_A	4'd2
`define OP_OR_AB	4'd3
`define OP_AND_AB	4'd4
`define OP_NOT_AB	4'd5
`define OP_EXOR		4'd6
`define OP_EXNOR	4'd7

module ALU (
	output reg c_out,
	output reg [7:0] sum,
	input [3:0] oper,
	input [7:0] a,
	input [7:0] b,
	input c_in
	
);
always @(*) begin
	case (oper)
		`OP_AND 	:	{c_out, sum} = a + b + c_in;
		`OP_SUBSTR 	:	{c_out, sum} = a + ~b + c_in;
		`OP_SUBSTR_A:	{c_out, sum} = b + ~a + ~c_in;
		`OP_OR_AB	:	{c_out, sum} = {1'b0, a | b};
		`OP_AND_AB	:	{c_out, sum} = {1'b0, a & b};
		`OP_NOT_AB	:	{c_out, sum} = {1'b0, (~a) & b};
		`OP_EXOR 	:	{c_out, sum} = {1'b0, a ^ b};
		`OP_EXNOR	:	{c_out, sum} = {1'b0, a ~^ b};
	
		default		:	{c_out, sum} = 9'bx;
	endcase

end


endmodule

Digital System Design/Assignments/part_2/project2_C/tb_ALU.v
//tb_ALU.v

`timescale 1 ns / 1 ns
`include "ALU.v"

module tb_ALU;

	wire [7:0] p_sum;
	wire p_cout;

	reg [7:0] p_a, p_b;
	reg [3:0] p_op;
	reg p_cin;

	ALU A1(
		.c_out(p_cout),
		.sum  (p_sum),
		.oper (p_op),
		.a    (p_a),
		.b    (p_b),
		.c_in (p_cin)
		);

	initial begin 
		$dumpfile("ALU.vcd");
		$dumpvars(0, tb_ALU);

		p_a = ($random) % 256;
		{p_cin, p_b} = ($random) % 512;

		p_op = 4'd0;

		repeat(79) begin 
			#10;

			p_a = ($random) % 256;
			{p_cin, p_b} = ($random) % 512;

			p_op = p_op + 1'b1;
		end

		#10 $stop;
	end

	initial begin 
		$monitor("oper = %d, a = %b, b = %b, c_out = %b, sum = %b.", p_op, p_a, p_b, p_cout, p_sum);
	end

endmodule

Digital System Design/Assignments/part_2/project2_C/ALU.vcd
$date
	Thu Dec 12 22:05:22 2019
$end
$version
	Icarus Verilog
$end
$timescale
	1ns
$end
$scope module tb_ALU $end
$var wire 8 ! p_sum [7:0] $end
$var wire 1 " p_cout $end
$var reg 8 # p_a [7:0] $end
$var reg 8 $ p_b [7:0] $end
$var reg 1 % p_cin $end
$var reg 4 & p_op [3:0] $end
$scope module A1 $end
$var wire 8 ' a [7:0] $end
$var wire 8 ( b [7:0] $end
$var wire 1 % c_in $end
$var wire 4 ) oper [3:0] $end
$var reg 1 " c_out $end
$var reg 8 * sum [7:0] $end
$upscope $end
$upscope $end
$enddefinitions $end
#0
$dumpvars
b10100101 *
b0 )
b10000001 (
b100100 '
b0 &
0%
b10000001 $
b100100 #
0"
b10100101 !
$end
#10
1"
b1 &
b1 )
b1100011 $
b1100011 (
b1001 #
b1001 '
#20
0"
b1111101 !
b1111101 *
b10 &
b10 )
1%
b10001101 $
b10001101 (
b1101 #
b1101 '
#30
b1110111 !
b1110111 *
b11 &
b11 )
0%
b10010 $
b10010 (
b1100101 #
b1100101 '
#40
b1 !
b1 *
b100 &
b100 )
1%
b1101 $
b1101 (
b1 #
b1 '
#50
b1001 !
b1001 *
b101 &
b101 )
b111101 $
b111101 (
b1110110 #
b1110110 '
#60
b1100001 !
b1100001 *
b110 &
b110 )
b10001100 $
b10001100 (
b11101101 #
b11101101 '
#70
b11000000 !
b11000000 *
b111 &
b111 )
0%
b11000110 $
b11000110 (
b11111001 #
b11111001 '
#80
x"
bx !
bx *
b1000 &
b1000 )
b10101010 $
b10101010 (
b11000101 #
b11000101 '
#90
b1001 &
b1001 )
b1110111 $
b1110111 (
b11100101 #
b11100101 '
#100
b1010 &
b1010 )
1%
b10001111 $
b10001111 (
b10010 #
b10010 '
#110
b1011 &
b1011 )
0%
b11001110 $
b11001110 (
b11110010 #
b11110010 '
#120
b1100 &
b1100 )
b11000101 $
b11000101 (
b11101000 #
b11101000 '
#130
b1101 &
b1101 )
b10111101 $
b10111101 (
b1011100 #
b1011100 '
#140
b1110 &
b1110 )
b1100101 $
b1100101 (
b101101 #
b101101 '
#150
b1111 &
b1111 )
1%
b1010 $
b1010 (
b1100011 #
b1100011 '
#160
0"
b10100001 !
b10100001 *
b0 &
b0 )
b100000 $
b100000 (
b10000000 #
b10000000 '
#170
b1100 !
b1100 *
b1 &
b1 )
0%
b10011101 $
b10011101 (
b10101010 #
b10101010 '
#180
1"
b1111011 !
b1111011 *
b10 &
b10 )
b10011 $
b10011 (
b10010110 #
b10010110 '
#190
0"
b1011111 !
b1011111 *
b11 &
b11 )
b1010011 $
b1010011 (
b1101 #
b1101 '
#200
b1000001 !
b1000001 *
b100 &
b100 )
b11010101 $
b11010101 (
b1101011 #
b1101011 '
#210
b10101100 !
b10101100 *
b101 &
b101 )
b10101110 $
b10101110 (
b10 #
b10 '
#220
b11010010 !
b11010010 *
b110 &
b110 )
b11001111 $
b11001111 (
b11101 #
b11101 '
#230
b11010110 !
b11010110 *
b111 &
b111 )
1%
b1010 $
b1010 (
b100011 #
b100011 '
#240
x"
bx !
bx *
b1000 &
b1000 )
0%
b111100 $
b111100 (
b11001010 #
b11001010 '
#250
b1001 &
b1001 )
1%
b10001010 $
b10001010 (
b11110010 #
b11110010 '
#260
b1010 &
b1010 )
0%
b11011000 $
b11011000 (
b1000001 #
b1000001 '
#270
b1011 &
b1011 )
b10001001 $
b10001001 (
b1111000 #
b1111000 '
#280
b1100 &
b1100 )
1%
b10110110 $
b10110110 (
b11101011 #
b11101011 '
#290
b1101 &
b1101 )
b10101110 $
b10101110 (
b11000110 #
b11000110 '
#300
b1110 &
b1110 )
b101010 $
b101010 (
b10111100 #
b10111100 '
#310
b1111 &
b1111 )
0%
b1110001 $
b1110001 (
b1011 #
b1011 '
#320
0"
b11010101 !
b11010101 *
b0 &
b0 )
1%
b1001111 $
b1001111 (
b10000101 #
b10000101 '
#330
b1 !
b1 *
b1 &
b1 )
b111010 $
b111010 (
b111011 #
b111011 '
#340
1"
b10010100 !
b10010100 *
b10 &
b10 )
b10101 $
b10101 (
b1111110 #
b1111110 '
#350
0"
b11111001 !
b11111001 *
b11 &
b11 )
b11011001 $
b11011001 (
b11110001 #
b11110001 '
#360
b1000000 !
b1000000 *
b100 &
b100 )
b1001100 $
b1001100 (
b1100010 #
b1100010 '
#370
b0 !
b0 *
b101 &
b101 )
b10001111 $
b10001111 (
b10011111 #
b10011111 '
#380
b1001111 !
b1001111 *
b110 &
b110 )
0%
b10110111 $
b10110111 (
b11111000 #
b11111000 '
#390
b111100 !
b111100 *
b111 &
b111 )
b1011100 $
b1011100 (
b10011111 #
b10011111 '
#400
x"
bx !
bx *
b1000 &
b1000 )
1%
b10001001 $
b10001001 (
b1011011 #
b1011011 '
#410
b1001 &
b1001 )
0%
b11010000 $
b11010000 (
b1001001 #
b1001001 '
#420
b1010 &
b1010 )
b1010001 $
b1010001 (
b11010111 #
b11010111 '
#430
b1011 &
b1011 )
1%
b1100 $
b1100 (
b10010110 #
b10010110 '
#440
b1100 &
b1100 )
b11001000 $
b11001000 (
b11000010 #
b11000010 '
#450
b1101 &
b1101 )
b111101 $
b111101 (
b1110111 #
b1110111 '
#460
b1110 &
b1110 )
0%
b1111110 $
b1111110 (
b10010 #
b10010 '
#470
b1111 &
b1111 )
1%
b111001 $
b111001 (
b1101101 #
b1101101 '
#480
0"
b11110010 !
b11110010 *
b0 &
b0 )
0%
b11010011 $
b11010011 (
b11111 #
b11111 '
#490
b1100 !
b1100 *
b1 &
b1 )
b1111000 $
b1111000 (
b10000101 #
b10000101 '
#500
1"
b11101011 !
b11101011 *
b10 &
b10 )
1%
b1001001 $
b1001001 (
b1011011 #
b1011011 '
#510
0"
b111111 !
b111111 *
b11 &
b11 )
b101010 $
b101010 (
b111111 #
b111111 '
#520
b0 !
b0 *
b100 &
b100 )
0%
b10000110 $
b10000110 (
b1011000 #
b1011000 '
#530
b10000 !
b10000 *
b101 &
b101 )
b10011100 $
b10011100 (
b10001110 #
b10001110 '
#540
b11011100 !
b11011100 *
b110 &
b110 )
b100110 $
b100110 (
b11111010 #
b11111010 '
#550
b101111 !
b101111 *
b111 &
b111 )
b10100011 $
b10100011 (
b1110011 #
b1110011 '
#560
x"
bx !
bx *
b1000 &
b1000 )
b10110011 $
b10110011 (
b101111 #
b101111 '
#570
b1001 &
b1001 )
1%
b1000100 $
b1000100 (
b1011111 #
b1011111 '
#580
b1010 &
b1010 )
0%
b11001011 $
b11001011 (
b11110111 #
b11110111 '
#590
b1011 &
b1011 )
1%
b1011010 $
b1011010 (
b11100110 #
b11100110 '
#600
b1100 &
b1100 )
0%
b11101101 $
b11101101 (
b101001 #
b101001 '
#610
b1101 &
b1101 )
b1100101 $
b1100101 (
b11011010 #
b11011010 '
#620
b1110 &
b1110 )
b11011111 $
b11011111 (
b10110101 #
b10110101 '
#630
b1111 &
b1111 )
1%
b1000100 $
b1000100 (
b1111001 #
b1111001 '
#640
0"
b11111011 !
b11111011 *
b0 &
b0 )
b101010 $
b101010 (
b11010000 #
b11010000 '
#650
b10011101 !
b10011101 *
b1 &
b1 )
b1110 $
b1110 (
b10101011 #
b10101011 '
#660
1"
b10111100 !
b10111100 *
b10 &
b10 )
0%
b10011010 $
b10011010 (
b11011100 #
b11011100 '
#670
0"
b11111111 !
b11111111 *
b11 &
b11 )
b11000011 $
b11000011 (
b11111101 #
b11111101 '
#680
b1000110 !
b1000110 *
b100 &
b100 )
1%
b1001110 $
b1001110 (
b1010110 #
b1010110 '
#690
b1000 !
b1000 *
b101 &
b101 )
0%
b1010 $
b1010 (
b1100111 #
b1100111 '
#700
b10001110 !
b10001110 *
b110 &
b110 )
b111000 $
b111000 (
b10110110 #
b10110110 '
#710
b111110 !
b111110 *
b111 &
b111 )
b10111000 $
b10111000 (
b1111001 #
b1111001 '
#720
x"
bx !
bx *
b1000 &
b1000 )
1%
b10010011 $
b10010011 (
b10010100 #
b10010100 '
#730
b1001 &
b1001 )
0%
b1011001 $
b1011001 (
b100 #
b100 '
#740
b1010 &
b1010 )
b1001101 $
b1001101 (
b11011011 #
b11011011 '
#750
b1011 &
b1011 )
b1101101 $
b1101101 (
b11011001 #
b11011001 '
#760
b1100 &
b1100 )
1%
b11001010 $
b11001010 (
b1110110 #
b1110110 '
#770
b1101 &
b1101 )
b10010101 $
b10010101 (
b10110110 #
b10110110 '
#780
b1110 &
b1110 )
b100 $
b100 (
b1000110 #
b1000110 '
#790
b1111 &
b1111 )
b1101001 $
b1101001 (
b11110111 #
b11110111 '
