Digital System Design/Assignments/part_2/project2_6/ones_count.v
//File: ones_count.v

`timescale 1 ns / 1 ns

module ones_count (
	output [3:0] count,
	input [7:0] dat_in
	
);
assign count =	dat_in[0] + dat_in[1] +
				dat_in[2] + dat_in[3] +
				dat_in[3] + dat_in[5] +
				dat_in[6] + dat_in[7];

endmodule

Digital System Design/Assignments/part_2/project2_6/tb_ones_count.v
//File: tb_ones_count.v

`timescale 1 ns / 1 ns
`include "ones_count.v"

module tb_ones_count;

	wire [3:0] p_cnt;

	reg [7:0] p_din;

	ones_count one1(
		.count(p_cnt),
		.dat_in(p_din)
		);

	initial
	begin 
		$dumpfile("ones_count.vcd");
		$dumpvars(0, tb_ones_count);

		p_din = 8'b0;
		repeat(255)
		begin 
			#10 p_din = p_din + 1;
		end

		#10 $stop;

	end

	initial
	begin 
		$monitor("At time %tns, dat_in = %b, count = %d", $time, p_din, p_cnt);
	end

endmodule

Digital System Design/Assignments/part_2/project2_6/ones_count.vcd
$date
	Thu Dec 12 20:33:06 2019
$end
$version
	Icarus Verilog
$end
$timescale
	1ns
$end
$scope module tb_ones_count $end
$var wire 4 ! p_cnt [3:0] $end
$var reg 8 " p_din [7:0] $end
$scope module one1 $end
$var wire 8 # dat_in [7:0] $end
$var wire 4 $ count [3:0] $end
$upscope $end
$upscope $end
$enddefinitions $end
#0
$dumpvars
b0 $
b0 #
b0 "
b0 !
$end
#10
b1 !
b1 $
b1 "
b1 #
#20
b1 !
b1 $
b10 "
b10 #
#30
b10 !
b10 $
b11 "
b11 #
#40
b1 !
b1 $
b100 "
b100 #
#50
b10 !
b10 $
b101 "
b101 #
#60
b10 !
b10 $
b110 "
b110 #
#70
b11 !
b11 $
b111 "
b111 #
#80
b10 !
b10 $
b1000 "
b1000 #
#90
b11 !
b11 $
b1001 "
b1001 #
#100
b11 !
b11 $
b1010 "
b1010 #
#110
b100 !
b100 $
b1011 "
b1011 #
#120
b11 !
b11 $
b1100 "
b1100 #
#130
b100 !
b100 $
b1101 "
b1101 #
#140
b100 !
b100 $
b1110 "
b1110 #
#150
b101 !
b101 $
b1111 "
b1111 #
#160
b0 !
b0 $
b10000 "
b10000 #
#170
b1 !
b1 $
b10001 "
b10001 #
#180
b1 !
b1 $
b10010 "
b10010 #
#190
b10 !
b10 $
b10011 "
b10011 #
#200
b1 !
b1 $
b10100 "
b10100 #
#210
b10 !
b10 $
b10101 "
b10101 #
#220
b10 !
b10 $
b10110 "
b10110 #
#230
b11 !
b11 $
b10111 "
b10111 #
#240
b10 !
b10 $
b11000 "
b11000 #
#250
b11 !
b11 $
b11001 "
b11001 #
#260
b11 !
b11 $
b11010 "
b11010 #
#270
b100 !
b100 $
b11011 "
b11011 #
#280
b11 !
b11 $
b11100 "
b11100 #
#290
b100 !
b100 $
b11101 "
b11101 #
#300
b100 !
b100 $
b11110 "
b11110 #
#310
b101 !
b101 $
b11111 "
b11111 #
#320
b1 !
b1 $
b100000 "
b100000 #
#330
b10 !
b10 $
b100001 "
b100001 #
#340
b10 !
b10 $
b100010 "
b100010 #
#350
b11 !
b11 $
b100011 "
b100011 #
#360
b10 !
b10 $
b100100 "
b100100 #
#370
b11 !
b11 $
b100101 "
b100101 #
#380
b11 !
b11 $
b100110 "
b100110 #
#390
b100 !
b100 $
b100111 "
b100111 #
#400
b11 !
b11 $
b101000 "
b101000 #
#410
b100 !
b100 $
b101001 "
b101001 #
#420
b100 !
b100 $
b101010 "
b101010 #
#430
b101 !
b101 $
b101011 "
b101011 #
#440
b100 !
b100 $
b101100 "
b101100 #
#450
b101 !
b101 $
b101101 "
b101101 #
#460
b101 !
b101 $
b101110 "
b101110 #
#470
b110 !
b110 $
b101111 "
b101111 #
#480
b1 !
b1 $
b110000 "
b110000 #
#490
b10 !
b10 $
b110001 "
b110001 #
#500
b10 !
b10 $
b110010 "
b110010 #
#510
b11 !
b11 $
b110011 "
b110011 #
#520
b10 !
b10 $
b110100 "
b110100 #
#530
b11 !
b11 $
b110101 "
b110101 #
#540
b11 !
b11 $
b110110 "
b110110 #
#550
b100 !
b100 $
b110111 "
b110111 #
#560
b11 !
b11 $
b111000 "
b111000 #
#570
b100 !
b100 $
b111001 "
b111001 #
#580
b100 !
b100 $
b111010 "
b111010 #
#590
b101 !
b101 $
b111011 "
b111011 #
#600
b100 !
b100 $
b111100 "
b111100 #
#610
b101 !
b101 $
b111101 "
b111101 #
#620
b101 !
b101 $
b111110 "
b111110 #
#630
b110 !
b110 $
b111111 "
b111111 #
#640
b1 !
b1 $
b1000000 "
b1000000 #
#650
b10 !
b10 $
b1000001 "
b1000001 #
#660
b10 !
b10 $
b1000010 "
b1000010 #
#670
b11 !
b11 $
b1000011 "
b1000011 #
#680
b10 !
b10 $
b1000100 "
b1000100 #
#690
b11 !
b11 $
b1000101 "
b1000101 #
#700
b11 !
b11 $
b1000110 "
b1000110 #
#710
b100 !
b100 $
b1000111 "
b1000111 #
#720
b11 !
b11 $
b1001000 "
b1001000 #
#730
b100 !
b100 $
b1001001 "
b1001001 #
#740
b100 !
b100 $
b1001010 "
b1001010 #
#750
b101 !
b101 $
b1001011 "
b1001011 #
#760
b100 !
b100 $
b1001100 "
b1001100 #
#770
b101 !
b101 $
b1001101 "
b1001101 #
#780
b101 !
b101 $
b1001110 "
b1001110 #
#790
b110 !
b110 $
b1001111 "
b1001111 #
#800
b1 !
b1 $
b1010000 "
b1010000 #
#810
b10 !
b10 $
b1010001 "
b1010001 #
#820
b10 !
b10 $
b1010010 "
b1010010 #
#830
b11 !
b11 $
b1010011 "
b1010011 #
#840
b10 !
b10 $
b1010100 "
b1010100 #
#850
b11 !
b11 $
b1010101 "
b1010101 #
#860
b11 !
b11 $
b1010110 "
b1010110 #
#870
b100 !
b100 $
b1010111 "
b1010111 #
#880
b11 !
b11 $
b1011000 "
b1011000 #
#890
b100 !
b100 $
b1011001 "
b1011001 #
#900
b100 !
b100 $
b1011010 "
b1011010 #
#910
b101 !
b101 $
b1011011 "
b1011011 #
#920
b100 !
b100 $
b1011100 "
b1011100 #
#930
b101 !
b101 $
b1011101 "
b1011101 #
#940
b101 !
b101 $
b1011110 "
b1011110 #
#950
b110 !
b110 $
b1011111 "
b1011111 #
#960
b10 !
b10 $
b1100000 "
b1100000 #
#970
b11 !
b11 $
b1100001 "
b1100001 #
#980
b11 !
b11 $
b1100010 "
b1100010 #
#990
b100 !
b100 $
b1100011 "
b1100011 #
#1000
b11 !
b11 $
b1100100 "
b1100100 #
#1010
b100 !
b100 $
b1100101 "
b1100101 #
#1020
b100 !
b100 $
b1100110 "
b1100110 #
#1030
b101 !
b101 $
b1100111 "
b1100111 #
#1040
b100 !
b100 $
b1101000 "
b1101000 #
#1050
b101 !
b101 $
b1101001 "
b1101001 #
#1060
b101 !
b101 $
b1101010 "
b1101010 #
#1070
b110 !
b110 $
b1101011 "
b1101011 #
#1080
b101 !
b101 $
b1101100 "
b1101100 #
#1090
b110 !
b110 $
b1101101 "
b1101101 #
#1100
b110 !
b110 $
b1101110 "
b1101110 #
#1110
b111 !
b111 $
b1101111 "
b1101111 #
#1120
b10 !
b10 $
b1110000 "
b1110000 #
#1130
b11 !
b11 $
b1110001 "
b1110001 #
#1140
b11 !
b11 $
b1110010 "
b1110010 #
#1150
b100 !
b100 $
b1110011 "
b1110011 #
#1160
b11 !
b11 $
b1110100 "
b1110100 #
#1170
b100 !
b100 $
b1110101 "
b1110101 #
#1180
b100 !
b100 $
b1110110 "
b1110110 #
#1190
b101 !
b101 $
b1110111 "
b1110111 #
#1200
b100 !
b100 $
b1111000 "
b1111000 #
#1210
b101 !
b101 $
b1111001 "
b1111001 #
#1220
b101 !
b101 $
b1111010 "
b1111010 #
#1230
b110 !
b110 $
b1111011 "
b1111011 #
#1240
b101 !
b101 $
b1111100 "
b1111100 #
#1250
b110 !
b110 $
b1111101 "
b1111101 #
#1260
b110 !
b110 $
b1111110 "
b1111110 #
#1270
b111 !
b111 $
b1111111 "
b1111111 #
#1280
b1 !
b1 $
b10000000 "
b10000000 #
#1290
b10 !
b10 $
b10000001 "
b10000001 #
#1300
b10 !
b10 $
b10000010 "
b10000010 #
#1310
b11 !
b11 $
b10000011 "
b10000011 #
#1320
b10 !
b10 $
b10000100 "
b10000100 #
#1330
b11 !
b11 $
b10000101 "
b10000101 #
#1340
b11 !
b11 $
b10000110 "
b10000110 #
#1350
b100 !
b100 $
b10000111 "
b10000111 #
#1360
b11 !
b11 $
b10001000 "
b10001000 #
#1370
b100 !
b100 $
b10001001 "
b10001001 #
#1380
b100 !
b100 $
b10001010 "
b10001010 #
#1390
b101 !
b101 $
b10001011 "
b10001011 #
#1400
b100 !
b100 $
b10001100 "
b10001100 #
#1410
b101 !
b101 $
b10001101 "
b10001101 #
#1420
b101 !
b101 $
b10001110 "
b10001110 #
#1430
b110 !
b110 $
b10001111 "
b10001111 #
#1440
b1 !
b1 $
b10010000 "
b10010000 #
#1450
b10 !
b10 $
b10010001 "
b10010001 #
#1460
b10 !
b10 $
b10010010 "
b10010010 #
#1470
b11 !
b11 $
b10010011 "
b10010011 #
#1480
b10 !
b10 $
b10010100 "
b10010100 #
#1490
b11 !
b11 $
b10010101 "
b10010101 #
#1500
b11 !
b11 $
b10010110 "
b10010110 #
#1510
b100 !
b100 $
b10010111 "
b10010111 #
#1520
b11 !
b11 $
b10011000 "
b10011000 #
#1530
b100 !
b100 $
b10011001 "
b10011001 #
#1540
b100 !
b100 $
b10011010 "
b10011010 #
#1550
b101 !
b101 $
b10011011 "
b10011011 #
#1560
b100 !
b100 $
b10011100 "
b10011100 #
#1570
b101 !
b101 $
b10011101 "
b10011101 #
#1580
b101 !
b101 $
b10011110 "
b10011110 #
#1590
b110 !
b110 $
b10011111 "
b10011111 #
#1600
b10 !
b10 $
b10100000 "
b10100000 #
#1610
b11 !
b11 $
b10100001 "
b10100001 #
#1620
b11 !
b11 $
b10100010 "
b10100010 #
#1630
b100 !
b100 $
b10100011 "
b10100011 #
#1640
b11 !
b11 $
b10100100 "
b10100100 #
#1650
b100 !
b100 $
b10100101 "
b10100101 #
#1660
b100 !
b100 $
b10100110 "
b10100110 #
#1670
b101 !
b101 $
b10100111 "
b10100111 #
#1680
b100 !
b100 $
b10101000 "
b10101000 #
#1690
b101 !
b101 $
b10101001 "
b10101001 #
#1700
b101 !
b101 $
b10101010 "
b10101010 #
#1710
b110 !
b110 $
b10101011 "
b10101011 #
#1720
b101 !
b101 $
b10101100 "
b10101100 #
#1730
b110 !
b110 $
b10101101 "
b10101101 #
#1740
b110 !
b110 $
b10101110 "
b10101110 #
#1750
b111 !
b111 $
b10101111 "
b10101111 #
#1760
b10 !
b10 $
b10110000 "
b10110000 #
#1770
b11 !
b11 $
b10110001 "
b10110001 #
#1780
b11 !
b11 $
b10110010 "
b10110010 #
#1790
b100 !
b100 $
b10110011 "
b10110011 #
#1800
b11 !
b11 $
b10110100 "
b10110100 #
#1810
b100 !
b100 $
b10110101 "
b10110101 #
#1820
b100 !
b100 $
b10110110 "
b10110110 #
#1830
b101 !
b101 $
b10110111 "
b10110111 #
#1840
b100 !
b100 $
b10111000 "
b10111000 #
#1850
b101 !
b101 $
b10111001 "
b10111001 #
#1860
b101 !
b101 $
b10111010 "
b10111010 #
#1870
b110 !
b110 $
b10111011 "
b10111011 #
#1880
b101 !
b101 $
b10111100 "
b10111100 #
#1890
b110 !
b110 $
b10111101 "
b10111101 #
#1900
b110 !
b110 $
b10111110 "
b10111110 #
#1910
b111 !
b111 $
b10111111 "
b10111111 #
#1920
b10 !
b10 $
b11000000 "
b11000000 #
#1930
b11 !
b11 $
b11000001 "
b11000001 #
#1940
b11 !
b11 $
b11000010 "
b11000010 #
#1950
b100 !
b100 $
b11000011 "
b11000011 #
#1960
b11 !
b11 $
b11000100 "
b11000100 #
#1970
b100 !
b100 $
b11000101 "
b11000101 #
#1980
b100 !
b100 $
b11000110 "
b11000110 #
#1990
b101 !
b101 $
b11000111 "
b11000111 #
#2000
b100 !
b100 $
b11001000 "
b11001000 #
#2010
b101 !
b101 $
b11001001 "
b11001001 #
#2020
b101 !
b101 $
b11001010 "
b11001010 #
#2030
b110 !
b110 $
b11001011 "
b11001011 #
#2040
b101 !
b101 $
b11001100 "
b11001100 #
#2050
b110 !
b110 $
b11001101 "
b11001101 #
#2060
b110 !
b110 $
b11001110 "
b11001110 #
#2070
b111 !
b111 $
b11001111 "
b11001111 #
#2080
b10 !
b10 $
b11010000 "
b11010000 #
#2090
b11 !
b11 $
b11010001 "
b11010001 #
#2100
b11 !
b11 $
b11010010 "
b11010010 #
#2110
b100 !
b100 $
b11010011 "
b11010011 #
#2120
b11 !
b11 $
b11010100 "
b11010100 #
#2130
b100 !
b100 $
b11010101 "
b11010101 #
#2140
b100 !
b100 $
b11010110 "
b11010110 #
#2150
b101 !
b101 $
b11010111 "
b11010111 #
#2160
b100 !
b100 $
b11011000 "
b11011000 #
#2170
b101 !
b101 $
b11011001 "
b11011001 #
#2180
b101 !
b101 $
b11011010 "
b11011010 #
#2190
b110 !
b110 $
b11011011 "
b11011011 #
#2200
b101 !
b101 $
b11011100 "
b11011100 #
#2210
b110 !
b110 $
b11011101 "
b11011101 #
#2220
b110 !
b110 $
b11011110 "
b11011110 #
#2230
b111 !
b111 $
b11011111 "
b11011111 #
#2240
b11 !
b11 $
b11100000 "
b11100000 #
#2250
b100 !
b100 $
b11100001 "
b11100001 #
#2260
b100 !
b100 $
b11100010 "
b11100010 #
#2270
b101 !
b101 $
b11100011 "
b11100011 #
#2280
b100 !
b100 $
b11100100 "
b11100100 #
#2290
b101 !
b101 $
b11100101 "
b11100101 #
#2300
b101 !
b101 $
b11100110 "
b11100110 #
#2310
b110 !
b110 $
b11100111 "
b11100111 #
#2320
b101 !
b101 $
b11101000 "
b11101000 #
#2330
b110 !
b110 $
b11101001 "
b11101001 #
#2340
b110 !
b110 $
b11101010 "
b11101010 #
#2350
b111 !
b111 $
b11101011 "
b11101011 #
#2360
b110 !
b110 $
b11101100 "
b11101100 #
#2370
b111 !
b111 $
b11101101 "
b11101101 #
#2380
b111 !
b111 $
b11101110 "
b11101110 #
#2390
b1000 !
b1000 $
b11101111 "
b11101111 #
#2400
b11 !
b11 $
b11110000 "
b11110000 #
#2410
b100 !
b100 $
b11110001 "
b11110001 #
#2420
b100 !
b100 $
b11110010 "
b11110010 #
#2430
b101 !
b101 $
b11110011 "
b11110011 #
#2440
b100 !
b100 $
b11110100 "
b11110100 #
#2450
b101 !
b101 $
b11110101 "
b11110101 #
#2460
b101 !
b101 $
b11110110 "
b11110110 #
#2470
b110 !
b110 $
b11110111 "
b11110111 #
#2480
b101 !
b101 $
b11111000 "
b11111000 #
#2490
b110 !
b110 $
b11111001 "
b11111001 #
#2500
b110 !
b110 $
b11111010 "
b11111010 #
#2510
b111 !
b111 $
b11111011 "
b11111011 #
#2520
b110 !
b110 $
b11111100 "
b11111100 #
#2530
b111 !
b111 $
b11111101 "
b11111101 #
#2540
b111 !
b111 $
b11111110 "
b11111110 #
#2550
b1000 !
b1000 $
b11111111 "
b11111111 #
