Digital System Design/Assignments/part_2/project2_1/wavegen.v
//File: wavegen.v
//517021911065 刘浩文

`timescale 10 ns / 1 ns

module wavegen;

	reg wave;

	initial
	begin 
		$dumpfile("wavegen.vcd");
		$dumpvars(0, wavegen);
	end

	initial
	fork
		wave = 1'b0;
		#2	wave = ~wave;
		#3	wave = ~wave;
		#12	wave = ~wave;
		#22	wave = ~wave;
		#24 wave = ~wave;
		#27 wave = ~wave;
		#32 wave = ~wave;
		#35 $stop;
	join

endmodule

Digital System Design/Assignments/part_2/project2_1/wavegen.vcd
$date
	Thu Dec 12 16:34:35 2019
$end
$version
	Icarus Verilog
$end
$timescale
	1ns
$end
$scope module wavegen $end
$var reg 1 ! wave $end
$upscope $end
$enddefinitions $end
#0
$dumpvars
0!
$end
#20
1!
#30
0!
#120
1!
#220
0!
#240
1!
#270
0!
#320
1!
