Digital System Design/Assignments/part_2/project2_3/mux2x1.v
//File: mux2x1.v
//517021911065 刘浩文

`timescale 1 ns / 1 ns

module mux2x1 (
	output dout,
	input sel,
	input [1:0] din
	
);
bufif0 b0(dout, din[0], sel);
bufif1 b1(dout, din[1], sel);

endmodule

Digital System Design/Assignments/part_2/project2_3/mux4x1.v
//File: mux4x1.v

`timescale 1 ns / 1 ns
`include "mux2x1.v"

module mux4x1 (
	output dout,
	input [1:0] sel,
	input [3:0] din
	
);
wire [1:0] dm;

wire [3:0] din1 = {din[3], din[1], din[2], din[0]};

mux2x1 m1(.dout(dm[0]),
	.sel(sel[1]),
	.din(din1[1:0]));

mux2x1 m2(.dout(dm[1]),
	.sel(sel[1]),
	.din(din1[3:2]));

mux2x1 m3(.dout(dout),
	.sel(sel[0]),
	.din(dm));

endmodule

Digital System Design/Assignments/part_2/project2_3/tb_mux4x1.v
//File: tb_mux4x1.v

`timescale 1 ns / 1 ns
`include "mux4x1.v"

module tb_mux4x1;

	wire p_dout;

	reg [3:0] p_din;
	reg [1:0] p_sel;

	mux4x1 m_m4x1(.dout(p_dout),
		.sel(p_sel),
		.din(p_din));

	initial
	begin 
		$dumpfile("mux4x1.vcd");
		$dumpvars(0, tb_mux4x1);

		p_din = 4'b0001;
		repeat(4)
		begin 
			p_sel = 2'b00;
			#10 p_sel = 2'b01;
			#10 p_sel = 2'b10;
			#10 p_sel = 2'b11;
			#10 p_din = p_din << 1;
		end

		#10 $stop;
	end

	initial
	begin 
		$monitor("in = %b, s = %b, out = %b.", p_din, p_sel, p_dout);
	end

endmodule

Digital System Design/Assignments/part_2/project2_3/mux4x1.vcd
$date
	Thu Dec 12 17:01:07 2019
$end
$version
	Icarus Verilog
$end
$timescale
	1ns
$end
$scope module tb_mux4x1 $end
$var wire 1 ! p_dout $end
$var reg 4 " p_din [3:0] $end
$var reg 2 # p_sel [1:0] $end
$scope module m_m4x1 $end
$var wire 4 $ din [3:0] $end
$var wire 1 ! dout $end
$var wire 2 % sel [1:0] $end
$var wire 2 & dm [1:0] $end
$var wire 4 ' din1 [3:0] $end
$scope module m1 $end
$var wire 2 ( din [1:0] $end
$var wire 1 ) dout $end
$var wire 1 * sel $end
$upscope $end
$scope module m2 $end
$var wire 2 + din [1:0] $end
$var wire 1 , dout $end
$var wire 1 - sel $end
$upscope $end
$scope module m3 $end
$var wire 2 . din [1:0] $end
$var wire 1 ! dout $end
$var wire 1 / sel $end
$upscope $end
$upscope $end
$upscope $end
$enddefinitions $end
#0
$dumpvars
0/
b1 .
0-
0,
b0 +
0*
1)
b1 (
b1 '
b1 &
b0 %
b1 $
b0 #
b1 "
1!
$end
#10
0!
1/
b1 #
b1 %
#20
b0 &
b0 .
0)
1*
1-
0!
0/
b10 #
b10 %
#30
1/
b11 #
b11 %
#40
b1 +
b0 (
0)
0*
b10 &
b10 .
1,
0-
0!
0/
b100 '
b0 #
b0 %
b10 "
b10 $
#50
1!
1/
b1 #
b1 %
#60
1*
b0 &
b0 .
0,
1-
0!
0/
b10 #
b10 %
#70
1/
b11 #
b11 %
#80
b0 +
b10 (
0)
0*
b0 &
b0 .
0,
0-
0!
0/
b10 '
b0 #
b0 %
b100 "
b100 $
#90
1/
b1 #
b1 %
#100
b1 &
b1 .
1)
1*
1-
1!
0/
b10 #
b10 %
#110
0!
1/
b11 #
b11 %
#120
b10 +
b0 (
0)
0*
b0 &
b0 .
0,
0-
0!
0/
b1000 '
b0 #
b0 %
b1000 "
b1000 $
#130
1/
b1 #
b1 %
#140
1*
b10 &
b10 .
1,
1-
0!
0/
b10 #
b10 %
#150
1!
1/
b11 #
b11 %
#160
0!
b0 &
b0 .
0,
b0 +
b0 '
b0 "
b0 $
