Digital System Design/Assignments/part_2/project2_9/LFSR.v
//File: LFSR.v

`timescale 1 ns / 1 ns

module LFSR (
	output reg [1:26] q,	// 26 bit data output.
	input clk,    			// Clock input.
	input rst_n,  			// Synchronous reset input active low.
	input load,				// Synchronous load input active high.
	input [1:26] din		// 26 bit parallel data input.
	
);
always @(posedge clk) begin
	if(~rst_n) q <= 26'b0;
	else begin 
		if(load) q <= (|din) ? din : 26'b1;
		else begin 
			if(!q) q <= 26'b1;
			else begin 
				q[1] <= q[26];
				q[2] <= q[1] ^ q[26];
				q[3:7] <= q[2:6];
				q[8] <= q[7] ^ q[26];
				q[9] <= q[8] ^ q[26];
				q[10:26] <= q[9:25];
			end
		end
	end
end


endmodule

Digital System Design/Assignments/part_2/project2_9/tb_LFSR.v
//File: tb_LFSR.v

`timescale 1 ns / 1 ns
`include "LFSR.v"

module tb_LFSR;

	wire [1:26] p_q;

	reg p_clk, p_rstn, p_load;
	reg [1:26] p_din;

	LFSR L1(
		.q    (p_q),
		.clk  (p_clk),
		.rst_n(p_rstn),
		.load (p_load),
		.din  (p_din)
		);

	initial begin 
		$dumpfile("LFSR.vcd");
		$dumpvars(0, tb_LFSR);

		p_clk = 1'b0;
		forever begin 
			#10 p_clk = ~p_clk;
		end
	end

	initial begin 
		p_rstn = 1'b0;
		#100 p_rstn = 1'b1;
	end

	initial begin 
		p_load = 1'b1;
		p_din = 26'd31;
		#155 p_load = 1'b0;

		#455 p_load = 1'b1;
		p_din = 26'd30;
		#505 p_load = 1'b0;

		#1005 p_load = 1'b1;
		p_din = 26'b0;
		#1055 p_load = 1'b0;

		#1500 $stop;
	end

	initial begin 
		$monitor("At time %tns, rst_n = %b, load = %b, q = %b.", $time, p_rstn, p_load, p_q);
	end

endmodule

Digital System Design/Assignments/part_2/project2_9/LFSR.vcd
$date
	Thu Dec 12 21:17:30 2019
$end
$version
	Icarus Verilog
$end
$timescale
	1ns
$end
$scope module tb_LFSR $end
$var wire 26 ! p_q [1:26] $end
$var reg 1 " p_clk $end
$var reg 26 # p_din [1:26] $end
$var reg 1 $ p_load $end
$var reg 1 % p_rstn $end
$scope module L1 $end
$var wire 1 " clk $end
$var wire 26 & din [1:26] $end
$var wire 1 $ load $end
$var wire 1 % rst_n $end
$var reg 26 ' q [1:26] $end
$upscope $end
$upscope $end
$enddefinitions $end
#0
$dumpvars
bx '
b11111 &
0%
1$
b11111 #
0"
bx !
$end
#10
b0 !
b0 '
1"
#20
0"
#30
1"
#40
0"
#50
1"
#60
0"
#70
1"
#80
0"
#90
1"
#100
0"
1%
#110
b11111 !
b11111 '
1"
#120
0"
#130
1"
#140
0"
#150
1"
#155
0$
#160
0"
#170
b11000001100000000000001111 !
b11000001100000000000001111 '
1"
#180
0"
#190
b10100001010000000000000111 !
b10100001010000000000000111 '
1"
#200
0"
#210
b10010001001000000000000011 !
b10010001001000000000000011 '
1"
#220
0"
#230
b10001001000100000000000001 !
b10001001000100000000000001 '
1"
#240
0"
#250
b10000101000010000000000000 !
b10000101000010000000000000 '
1"
#260
0"
#270
b1000010100001000000000000 !
b1000010100001000000000000 '
1"
#280
0"
#290
b100001010000100000000000 !
b100001010000100000000000 '
1"
#300
0"
#310
b10000101000010000000000 !
b10000101000010000000000 '
1"
#320
0"
#330
b1000010100001000000000 !
b1000010100001000000000 '
1"
#340
0"
#350
b100001010000100000000 !
b100001010000100000000 '
1"
#360
0"
#370
b10000101000010000000 !
b10000101000010000000 '
1"
#380
0"
#390
b1000010100001000000 !
b1000010100001000000 '
1"
#400
0"
#410
b100001010000100000 !
b100001010000100000 '
1"
#420
0"
#430
b10000101000010000 !
b10000101000010000 '
1"
#440
0"
#450
b1000010100001000 !
b1000010100001000 '
1"
#460
0"
#470
b100001010000100 !
b100001010000100 '
1"
#480
0"
#490
b10000101000010 !
b10000101000010 '
1"
#500
0"
#510
b1000010100001 !
b1000010100001 '
1"
#520
0"
#530
b11000001100000100001010000 !
b11000001100000100001010000 '
1"
#540
0"
#550
b1100000110000010000101000 !
b1100000110000010000101000 '
1"
#560
0"
#570
b110000011000001000010100 !
b110000011000001000010100 '
1"
#580
0"
#590
b11000001100000100001010 !
b11000001100000100001010 '
1"
#600
0"
#610
b11110 !
b11110 '
1"
b11110 #
b11110 &
1$
