Digital System Design/Assignments/part_2/project2_4/comb_prim.v
//File: comb_prim.v

`timescale 1 ns / 1 ns

primitive prim_udp(output Y,
	input A, 
	input B, 
	input C, 
	input D
	);
table
	//	A B C D : Y
		0 0 0 0 : 0;
		0 0 0 1 : 0;
		0 0 1 0 : 0;
		0 0 1 1 : 0;
		0 1 0 0 : 0;
		0 1 0 1 : 0;
		0 1 1 0 : 1;
		0 1 1 1 : 0;
		1 0 0 0 : 0;
		1 0 0 1 : 0;
		1 0 1 0 : 0;
		1 0 1 1 : 0;
		1 1 0 0 : 0;
		1 1 0 1 : 0;
		1 1 1 0 : 0;
		1 1 1 1 : 0;
endtable

endprimitive


module comb_prim (
	output Y,
	input A, B, C, D
	
);
prim_udp(Y, A, B, C, D);

endmodule

Digital System Design/Assignments/part_2/project2_4/comb_behavior.v
//File: comb_behavior.v

`timescale 1 ns / 1 ns

module comb_behavior (
	output reg Y,
	input A, B, C, D
	
);
reg u1, u2, u3, u4;

always @(*) begin
	
	u1 = ~D;
	u4 = B & C & u1;
	u3 = A | D;
	u2 = ~u3;
	Y = u2 & u4;

end

endmodule

Digital System Design/Assignments/part_2/project2_4/comb_dataflow.v
//File: comb_dataflow.v

`timescale 1 ns / 1 ns

module comb_dataflow (
	output Y,
	input A, B, C, D
);
wire u1, u2, u3, u4;

assign	u1 = ~D,	u4 = B & C & u1,
		u3 = A | D,	u2 = ~u3,
		Y = u2 & u4;

endmodule

Digital System Design/Assignments/part_2/project2_4/comb_str.v
//File: comb_str.v

`timescale 1 ns / 1 ns

module comb_str (
	output Y,
	input A, B, C, D
	
);
wire u1, u2, u3, u4;

not n1(u1, D);
and a1(u4, B, C, u1);
or o1(u3, A, D);
not n2(u2, u3);
and a2(Y, u2, u4);

endmodule

Digital System Design/Assignments/part_2/project2_4/testbench_comb.v
//File: testbench_comb.v

`timescale 1 ns / 1 ns
`include "comb_str.v"
`include "comb_dataflow.v"
`include "comb_behavior.v"
`include "comb_prim.v"

module testbench_comb;

	wire [3:0] p_Y;

	reg p_A, p_B, p_C, p_D;

	reg [3:0] temp;

	comb_str c1(.Y(p_Y[0]),
		.A(p_A), .B(p_B), .C(p_C), .D(p_D));

	comb_dataflow c2(.Y(p_Y[1]),
		.A(p_A), .B(p_B), .C(p_C), .D(p_D));

	comb_behavior c3(.Y(p_Y[2]),
		.A(p_A), .B(p_B), .C(p_C), .D(p_D));

	comb_prim c4(.Y(p_Y[3]),
		.A(p_A), .B(p_B), .C(p_C), .D(p_D));

	initial
	begin 
		$dumpfile("comb.vcd");
		$dumpvars(0, testbench_comb);

		temp = 4'b0;
		repeat(15) 
		begin
			{p_A, p_B, p_C, p_D} = temp;
			#10 temp = temp + 1;
		end
		{p_A, p_B, p_C, p_D} = temp;

		#10 $stop;

	end

	initial
	begin 
		$monitor("At time %t, A = %b, B = %b, C = %b, D = %b, Y_str = %b, Y_df = %b, Y_bh = %b, Y_pr = %b.", $time, p_A, p_B, p_C, p_D, p_Y[0], p_Y[1], p_Y[2], p_Y[3]);
	end

endmodule

Digital System Design/Assignments/part_2/project2_4/comb.vcd
$date
	Thu Dec 12 17:10:03 2019
$end
$version
	Icarus Verilog
$end
$timescale
	1ns
$end
$scope module testbench_comb $end
$var wire 4 ! p_Y [3:0] $end
$var reg 1 " p_A $end
$var reg 1 # p_B $end
$var reg 1 $ p_C $end
$var reg 1 % p_D $end
$var reg 4 & temp [3:0] $end
$scope module c1 $end
$var wire 1 " A $end
$var wire 1 # B $end
$var wire 1 $ C $end
$var wire 1 % D $end
$var wire 1 ' Y $end
$var wire 1 ( u1 $end
$var wire 1 ) u2 $end
$var wire 1 * u3 $end
$var wire 1 + u4 $end
$upscope $end
$scope module c2 $end
$var wire 1 " A $end
$var wire 1 # B $end
$var wire 1 $ C $end
$var wire 1 % D $end
$var wire 1 , Y $end
$var wire 1 - u1 $end
$var wire 1 . u2 $end
$var wire 1 / u3 $end
$var wire 1 0 u4 $end
$upscope $end
$scope module c3 $end
$var wire 1 " A $end
$var wire 1 # B $end
$var wire 1 $ C $end
$var wire 1 % D $end
$var reg 1 1 Y $end
$var reg 1 2 u1 $end
$var reg 1 3 u2 $end
$var reg 1 4 u3 $end
$var reg 1 5 u4 $end
$upscope $end
$scope module c4 $end
$var wire 1 " A $end
$var wire 1 # B $end
$var wire 1 $ C $end
$var wire 1 % D $end
$var wire 1 6 Y $end
$upscope $end
$upscope $end
$enddefinitions $end
#0
$dumpvars
06
05
04
13
12
01
00
0/
1.
1-
0,
0+
0*
1)
1(
0'
b0 &
0%
0$
0#
0"
b0 !
$end
#10
0)
0.
0(
1*
0-
1/
03
14
02
1%
b1 &
#20
1)
1.
1(
0*
1-
0/
13
04
12
1$
0%
b10 &
#30
0)
0.
0(
1*
0-
1/
03
14
02
1%
b11 &
#40
1)
1.
1(
0*
1-
0/
13
04
12
1#
0$
0%
b100 &
#50
0)
0.
0(
1*
0-
1/
03
14
02
1%
b101 &
#60
1,
1'
1)
10
1.
1+
16
1(
0*
1-
0/
b1111 !
11
13
04
15
12
1$
0%
b110 &
#70
0'
0,
0+
0)
00
0.
0(
1*
0-
1/
01
03
14
05
02
b0 !
06
1%
b111 &
#80
1(
1-
12
1"
0#
0$
0%
b1000 &
#90
0(
0-
02
1%
b1001 &
#100
1(
1-
12
1$
0%
b1010 &
#110
0(
0-
02
1%
b1011 &
#120
1(
1-
12
1#
0$
0%
b1100 &
#130
0(
0-
02
1%
b1101 &
#140
10
1+
1(
1-
15
12
1$
0%
b1110 &
#150
0+
00
0(
0-
05
02
1%
b1111 &
