Digital System Design/Assignments/part_2/project2_5/comb_Y.v
//File: comb_Y.v

`timescale 1 ns / 1 ns

module comb_Y1 (
	output	Y,
	input	A, B, C
	
);
assign	Y = ~A & ~B & C 
		| ~A & B & ~C 
		| A & ~B & ~C 
		| A & ~B & C;

endmodule

module comb_Y2 (
	output	Y,
	input	A, B, C, D
	
);
assign	Y = ~A & B & ~C & ~D 
		| ~A & B & ~C & D 
		| ~A & B & C & ~D 
		| ~A & B & C & D 
		| A & ~B & C & D 
		| A & B & ~C & ~D 
		| A & B & ~C & D;

endmodule

Digital System Design/Assignments/part_2/project2_5/tb_comb_Y1.v
//File: tb_comb_Y1.v

`timescale 1 ns / 1 ns
`include "comb_Y.v"

module tb_comb_Y1;

	wire p_Y;

	reg p_A, p_B, p_C;

	reg [2:0] temp;

	comb_Y1 c1(
		.Y(p_Y),
		.A(p_A),
		.B(p_B),
		.C(p_C)
		);

	initial
	begin 
		$dumpfile("comb_Y1.vcd");
		$dumpvars(0, tb_comb_Y1);

		temp = 3'b0;
		repeat(7)
		begin 
			{p_A, p_B, p_C} = temp;
			#10 temp = temp + 1;
		end
		{p_A, p_B, p_C} = temp;

		#10 $stop;
	end

	initial
	begin 
		$monitor("At time %t, A = %b, B = %b, C = %b, Y = %b.", $time, p_A, p_B, p_C, p_Y);
	end

endmodule

Digital System Design/Assignments/part_2/project2_5/comb_Y1.vcd
$date
	Thu Dec 12 17:15:55 2019
$end
$version
	Icarus Verilog
$end
$timescale
	1ns
$end
$scope module tb_comb_Y1 $end
$var wire 1 ! p_Y $end
$var reg 1 " p_A $end
$var reg 1 # p_B $end
$var reg 1 $ p_C $end
$var reg 3 % temp [2:0] $end
$scope module c1 $end
$var wire 1 " A $end
$var wire 1 # B $end
$var wire 1 $ C $end
$var wire 1 ! Y $end
$upscope $end
$upscope $end
$enddefinitions $end
#0
$dumpvars
b0 %
0$
0#
0"
0!
$end
#10
1!
1$
b1 %
#20
1#
0$
b10 %
#30
0!
1$
b11 %
#40
1!
1"
0#
0$
b100 %
#50
1$
b101 %
#60
0!
1#
0$
b110 %
#70
1$
b111 %
