Digital System Design/Assignments/part_2/project2_5/comb_Y.v
//File: comb_Y.v

`timescale 1 ns / 1 ns

module comb_Y1 (
	output	Y,
	input	A, B, C
	
);
assign	Y = ~A & ~B & C 
		| ~A & B & ~C 
		| A & ~B & ~C 
		| A & ~B & C;

endmodule

module comb_Y2 (
	output	Y,
	input	A, B, C, D
	
);
assign	Y = ~A & B & ~C & ~D 
		| ~A & B & ~C & D 
		| ~A & B & C & ~D 
		| ~A & B & C & D 
		| A & ~B & C & D 
		| A & B & ~C & ~D 
		| A & B & ~C & D;

endmodule

Digital System Design/Assignments/part_2/project2_5/tb_comb_Y2.v
//File: tb_comb_Y2.v

`timescale 1 ns / 1 ns
`include "comb_Y.v"

module tb_comb_Y2;

	wire p_Y;

	reg p_A, p_B, p_C, p_D;

	reg [3:0] temp;

	comb_Y2 c2(
		.Y(p_Y),
		.A(p_A),
		.B(p_B),
		.C(p_C),
		.D(p_D)
		);

	initial
	begin 
		$dumpfile("comb_Y2.vcd");
		$dumpvars(0, tb_comb_Y2);

		temp = 4'b0;
		repeat(15)
		begin 
			{p_A, p_B, p_C, p_D} = temp;
			#10 temp = temp + 1;
		end
		{p_A, p_B, p_C, p_D} = temp;

		#10 $stop;
	end

	initial
	begin 
		$monitor("At time %t, A = %b, B = %b, C = %b, D = %b, Y = %b.", $time, p_A, p_B, p_C, p_D, p_Y);
	end

endmodule

Digital System Design/Assignments/part_2/project2_5/comb_Y2.vcd
$date
	Thu Dec 12 17:17:19 2019
$end
$version
	Icarus Verilog
$end
$timescale
	1ns
$end
$scope module tb_comb_Y2 $end
$var wire 1 ! p_Y $end
$var reg 1 " p_A $end
$var reg 1 # p_B $end
$var reg 1 $ p_C $end
$var reg 1 % p_D $end
$var reg 4 & temp [3:0] $end
$scope module c2 $end
$var wire 1 " A $end
$var wire 1 # B $end
$var wire 1 $ C $end
$var wire 1 % D $end
$var wire 1 ! Y $end
$upscope $end
$upscope $end
$enddefinitions $end
#0
$dumpvars
b0 &
0%
0$
0#
0"
0!
$end
#10
1%
b1 &
#20
1$
0%
b10 &
#30
1%
b11 &
#40
1!
1#
0$
0%
b100 &
#50
1%
b101 &
#60
1$
0%
b110 &
#70
1%
b111 &
#80
0!
1"
0#
0$
0%
b1000 &
#90
1%
b1001 &
#100
1$
0%
b1010 &
#110
1!
1%
b1011 &
#120
1!
1#
0$
0%
b1100 &
#130
1%
b1101 &
#140
0!
1$
0%
b1110 &
#150
1%
b1111 &
