Digital System Design/Assignments/part_2/project2_7/dec_counter.v
//File: dec_counter.v

`timescale 10 ns / 1 ns

module dec_counter (
	output reg [3:0] counter,
	input clk,    // Clock
	input reset  // Asynchronous reset active low
	
);
always @(posedge clk) 
begin
	if(~reset)
		counter <= 4'd0;
	else if(counter == 4'd9)
		counter <= 4'd0;
	else counter = counter + 4'd1;

end


endmodule

Digital System Design/Assignments/part_2/project2_7/tb_dec_counter.v
//File: tb_dec_counter.v

`timescale 10 ns / 1 ns
`include "dec_counter.v"

module tb_dec_counter;

	wire [3:0] p_counter;

	reg p_clk, p_reset;

	dec_counter m_decc(
		.counter(p_counter),
		.clk    (p_clk),
		.reset  (p_reset)
		);

	initial
	begin 
		$dumpfile("dec_counter.vcd");
		$dumpvars(0, tb_dec_counter);

		p_clk = 1'b0;
		forever
		begin 
			#10 p_clk = ~p_clk;
		end

	end

	initial
	begin 
		p_reset = 1'b0;
		#100 p_reset = 1'b1;
		#1000 $stop;

	end

	initial
	begin 
		$monitor("At time %tns, reset = %b, counter = %d.", $time, p_reset, p_counter);
	end

endmodule

Digital System Design/Assignments/part_2/project2_7/dec_counter.vcd
$date
	Thu Dec 12 20:47:43 2019
$end
$version
	Icarus Verilog
$end
$timescale
	1ns
$end
$scope module tb_dec_counter $end
$var wire 4 ! p_counter [3:0] $end
$var reg 1 " p_clk $end
$var reg 1 # p_reset $end
$scope module m_decc $end
$var wire 1 " clk $end
$var wire 1 # reset $end
$var reg 4 $ counter [3:0] $end
$upscope $end
$upscope $end
$enddefinitions $end
#0
$dumpvars
bx $
0#
0"
bx !
$end
#100
b0 !
b0 $
1"
#200
0"
#300
1"
#400
0"
#500
1"
#600
0"
#700
1"
#800
0"
#900
1"
#1000
0"
1#
#1100
b1 !
b1 $
1"
#1200
0"
#1300
b10 !
b10 $
1"
#1400
0"
#1500
b11 !
b11 $
1"
#1600
0"
#1700
b100 !
b100 $
1"
#1800
0"
#1900
b101 !
b101 $
1"
#2000
0"
#2100
b110 !
b110 $
1"
#2200
0"
#2300
b111 !
b111 $
1"
#2400
0"
#2500
b1000 !
b1000 $
1"
#2600
0"
#2700
b1001 !
b1001 $
1"
#2800
0"
#2900
b0 !
b0 $
1"
#3000
0"
#3100
b1 !
b1 $
1"
#3200
0"
#3300
b10 !
b10 $
1"
#3400
0"
#3500
b11 !
b11 $
1"
#3600
0"
#3700
b100 !
b100 $
1"
#3800
0"
#3900
b101 !
b101 $
1"
#4000
0"
#4100
b110 !
b110 $
1"
#4200
0"
#4300
b111 !
b111 $
1"
#4400
0"
#4500
b1000 !
b1000 $
1"
#4600
0"
#4700
b1001 !
b1001 $
1"
#4800
0"
#4900
b0 !
b0 $
1"
#5000
0"
#5100
b1 !
b1 $
1"
#5200
0"
#5300
b10 !
b10 $
1"
#5400
0"
#5500
b11 !
b11 $
1"
#5600
0"
#5700
b100 !
b100 $
1"
#5800
0"
#5900
b101 !
b101 $
1"
#6000
0"
#6100
b110 !
b110 $
1"
#6200
0"
#6300
b111 !
b111 $
1"
#6400
0"
#6500
b1000 !
b1000 $
1"
#6600
0"
#6700
b1001 !
b1001 $
1"
#6800
0"
#6900
b0 !
b0 $
1"
#7000
0"
#7100
b1 !
b1 $
1"
#7200
0"
#7300
b10 !
b10 $
1"
#7400
0"
#7500
b11 !
b11 $
1"
#7600
0"
#7700
b100 !
b100 $
1"
#7800
0"
#7900
b101 !
b101 $
1"
#8000
0"
#8100
b110 !
b110 $
1"
#8200
0"
#8300
b111 !
b111 $
1"
#8400
0"
#8500
b1000 !
b1000 $
1"
#8600
0"
#8700
b1001 !
b1001 $
1"
#8800
0"
#8900
b0 !
b0 $
1"
#9000
0"
#9100
b1 !
b1 $
1"
#9200
0"
#9300
b10 !
b10 $
1"
#9400
0"
#9500
b11 !
b11 $
1"
#9600
0"
#9700
b100 !
b100 $
1"
#9800
0"
#9900
b101 !
b101 $
1"
#10000
0"
#10100
b110 !
b110 $
1"
#10200
0"
#10300
b111 !
b111 $
1"
#10400
0"
#10500
b1000 !
b1000 $
1"
#10600
0"
#10700
b1001 !
b1001 $
1"
#10800
0"
#10900
b0 !
b0 $
1"
