Digital System Design/Assignments/part_2/project2_D/shift_counter.v
//File: shift_counter.v

`timescale 1 ns / 1 ns

module shift_counter (
	output reg [7:0] count,
	input clk,    // Clock
	input reset  // Synchronous reset active low
	
);
reg [13:0] temp;

always @(posedge clk) begin
	if(~reset) begin
		count <= 8'b1;
		temp <= 14'b1;
	end else begin
		temp <= {temp[12:0], temp[13]};
		if(|temp[13:8])
			count <= {temp[7], temp[8], temp[9], temp[10], temp[11], temp[12], temp[13], 1'b0};
		else count <= temp[7:0];
	end
end

endmodule

Digital System Design/Assignments/part_2/project2_D/tb_shift_counter.v
//tb_shift_counter.v

`timescale 1 ns / 1 ns

`include "shift_counter.v"

module tb_shift_counter;

	wire [7:0] p_cnt;

	reg p_clk, p_rst;

	shift_counter shc1(
		.count(p_cnt),
		.clk  (p_clk),
		.reset(p_rst)
		);

	initial begin 
		$dumpfile("shift_counter.vcd");
		$dumpvars(0, tb_shift_counter);

		p_clk = 1'b0;
		forever begin 
			#10 p_clk = ~p_clk;
		end
	end

	initial begin 
		p_rst = 1'b0;
		#55 p_rst = 1'b1;

		#2000 $stop;
	end

	initial begin 
		$monitor("At time %tns, reset = %b, count = %b", $time, p_rst, p_cnt);
	end

endmodule

Digital System Design/Assignments/part_2/project2_D/shift_counter.vcd
$date
	Thu Dec 12 22:16:55 2019
$end
$version
	Icarus Verilog
$end
$timescale
	1ns
$end
$scope module tb_shift_counter $end
$var wire 8 ! p_cnt [7:0] $end
$var reg 1 " p_clk $end
$var reg 1 # p_rst $end
$scope module shc1 $end
$var wire 1 " clk $end
$var wire 1 # reset $end
$var reg 8 $ count [7:0] $end
$var reg 14 % temp [13:0] $end
$upscope $end
$upscope $end
$enddefinitions $end
#0
$dumpvars
bx %
bx $
0#
0"
bx !
$end
#10
b1 %
b1 !
b1 $
1"
#20
0"
#30
1"
#40
0"
#50
1"
#55
1#
#60
0"
#70
b10 %
1"
#80
0"
#90
b10 !
b10 $
b100 %
1"
#100
0"
#110
b100 !
b100 $
b1000 %
1"
#120
0"
#130
b1000 !
b1000 $
b10000 %
1"
#140
0"
#150
b10000 !
b10000 $
b100000 %
1"
#160
0"
#170
b100000 !
b100000 $
b1000000 %
1"
#180
0"
#190
b1000000 !
b1000000 $
b10000000 %
1"
#200
0"
#210
b10000000 !
b10000000 $
b100000000 %
1"
#220
0"
#230
b1000000 !
b1000000 $
b1000000000 %
1"
#240
0"
#250
b100000 !
b100000 $
b10000000000 %
1"
#260
0"
#270
b10000 !
b10000 $
b100000000000 %
1"
#280
0"
#290
b1000 !
b1000 $
b1000000000000 %
1"
#300
0"
#310
b100 !
b100 $
b10000000000000 %
1"
#320
0"
#330
b10 !
b10 $
b1 %
1"
#340
0"
#350
b1 !
b1 $
b10 %
1"
#360
0"
#370
b10 !
b10 $
b100 %
1"
#380
0"
#390
b100 !
b100 $
b1000 %
1"
#400
0"
#410
b1000 !
b1000 $
b10000 %
1"
#420
0"
#430
b10000 !
b10000 $
b100000 %
1"
#440
0"
#450
b100000 !
b100000 $
b1000000 %
1"
#460
0"
#470
b1000000 !
b1000000 $
b10000000 %
1"
#480
0"
#490
b10000000 !
b10000000 $
b100000000 %
1"
#500
0"
#510
b1000000 !
b1000000 $
b1000000000 %
1"
#520
0"
#530
b100000 !
b100000 $
b10000000000 %
1"
#540
0"
#550
b10000 !
b10000 $
b100000000000 %
1"
#560
0"
#570
b1000 !
b1000 $
b1000000000000 %
1"
#580
0"
#590
b100 !
b100 $
b10000000000000 %
1"
#600
0"
#610
b10 !
b10 $
b1 %
1"
#620
0"
#630
b1 !
b1 $
b10 %
1"
#640
0"
#650
b10 !
b10 $
b100 %
1"
#660
0"
#670
b100 !
b100 $
b1000 %
1"
#680
0"
#690
b1000 !
b1000 $
b10000 %
1"
#700
0"
#710
b10000 !
b10000 $
b100000 %
1"
#720
0"
#730
b100000 !
b100000 $
b1000000 %
1"
#740
0"
#750
b1000000 !
b1000000 $
b10000000 %
1"
#760
0"
#770
b10000000 !
b10000000 $
b100000000 %
1"
#780
0"
#790
b1000000 !
b1000000 $
b1000000000 %
1"
#800
0"
#810
b100000 !
b100000 $
b10000000000 %
1"
#820
0"
#830
b10000 !
b10000 $
b100000000000 %
1"
#840
0"
#850
b1000 !
b1000 $
b1000000000000 %
1"
#860
0"
#870
b100 !
b100 $
b10000000000000 %
1"
#880
0"
#890
b10 !
b10 $
b1 %
1"
#900
0"
#910
b1 !
b1 $
b10 %
1"
#920
0"
#930
b10 !
b10 $
b100 %
1"
#940
0"
#950
b100 !
b100 $
b1000 %
1"
#960
0"
#970
b1000 !
b1000 $
b10000 %
1"
#980
0"
#990
b10000 !
b10000 $
b100000 %
1"
#1000
0"
#1010
b100000 !
b100000 $
b1000000 %
1"
#1020
0"
#1030
b1000000 !
b1000000 $
b10000000 %
1"
#1040
0"
#1050
b10000000 !
b10000000 $
b100000000 %
1"
#1060
0"
#1070
b1000000 !
b1000000 $
b1000000000 %
1"
#1080
0"
#1090
b100000 !
b100000 $
b10000000000 %
1"
#1100
0"
#1110
b10000 !
b10000 $
b100000000000 %
1"
#1120
0"
#1130
b1000 !
b1000 $
b1000000000000 %
1"
#1140
0"
#1150
b100 !
b100 $
b10000000000000 %
1"
#1160
0"
#1170
b10 !
b10 $
b1 %
1"
#1180
0"
#1190
b1 !
b1 $
b10 %
1"
#1200
0"
#1210
b10 !
b10 $
b100 %
1"
#1220
0"
#1230
b100 !
b100 $
b1000 %
1"
#1240
0"
#1250
b1000 !
b1000 $
b10000 %
1"
#1260
0"
#1270
b10000 !
b10000 $
b100000 %
1"
#1280
0"
#1290
b100000 !
b100000 $
b1000000 %
1"
#1300
0"
#1310
b1000000 !
b1000000 $
b10000000 %
1"
#1320
0"
#1330
b10000000 !
b10000000 $
b100000000 %
1"
#1340
0"
#1350
b1000000 !
b1000000 $
b1000000000 %
1"
#1360
0"
#1370
b100000 !
b100000 $
b10000000000 %
1"
#1380
0"
#1390
b10000 !
b10000 $
b100000000000 %
1"
#1400
0"
#1410
b1000 !
b1000 $
b1000000000000 %
1"
#1420
0"
#1430
b100 !
b100 $
b10000000000000 %
1"
#1440
0"
#1450
b10 !
b10 $
b1 %
1"
#1460
0"
#1470
b1 !
b1 $
b10 %
1"
#1480
0"
#1490
b10 !
b10 $
b100 %
1"
#1500
0"
#1510
b100 !
b100 $
b1000 %
1"
#1520
0"
#1530
b1000 !
b1000 $
b10000 %
1"
#1540
0"
#1550
b10000 !
b10000 $
b100000 %
1"
#1560
0"
#1570
b100000 !
b100000 $
b1000000 %
1"
#1580
0"
#1590
b1000000 !
b1000000 $
b10000000 %
1"
#1600
0"
#1610
b10000000 !
b10000000 $
b100000000 %
1"
#1620
0"
#1630
b1000000 !
b1000000 $
b1000000000 %
1"
#1640
0"
#1650
b100000 !
b100000 $
b10000000000 %
1"
#1660
0"
#1670
b10000 !
b10000 $
b100000000000 %
1"
#1680
0"
#1690
b1000 !
b1000 $
b1000000000000 %
1"
#1700
0"
#1710
b100 !
b100 $
b10000000000000 %
1"
#1720
0"
#1730
b10 !
b10 $
b1 %
1"
#1740
0"
#1750
b1 !
b1 $
b10 %
1"
#1760
0"
#1770
b10 !
b10 $
b100 %
1"
#1780
0"
#1790
b100 !
b100 $
b1000 %
1"
#1800
0"
#1810
b1000 !
b1000 $
b10000 %
1"
#1820
0"
#1830
b10000 !
b10000 $
b100000 %
1"
#1840
0"
#1850
b100000 !
b100000 $
b1000000 %
1"
#1860
0"
#1870
b1000000 !
b1000000 $
b10000000 %
1"
#1880
0"
#1890
b10000000 !
b10000000 $
b100000000 %
1"
#1900
0"
#1910
b1000000 !
b1000000 $
b1000000000 %
1"
#1920
0"
#1930
b100000 !
b100000 $
b10000000000 %
1"
#1940
0"
#1950
b10000 !
b10000 $
b100000000000 %
1"
#1960
0"
#1970
b1000 !
b1000 $
b1000000000000 %
1"
#1980
0"
#1990
b100 !
b100 $
b10000000000000 %
1"
#2000
0"
#2010
b10 !
b10 $
b1 %
1"
#2020
0"
#2030
b1 !
b1 $
b10 %
1"
#2040
0"
#2050
b10 !
b10 $
b100 %
1"
