Digital System Design/Assignments/part_2/project2_G/moore.v
//File: moore.v

`timescale 1 ns / 100 ps 

module moore (
	output reg flag,
	input din,
	input clk,
	input rst
	
);
parameter	IDLE= 9'b0_0000_0001,
			A	= 9'b0_0000_0010,
			B 	= 9'b0_0000_0100,
			C 	= 9'b0_0000_1000,
			D 	= 9'b0_0001_0000,
			E 	= 9'b0_0010_0000,
			F 	= 9'b0_0100_0000,
			G 	= 9'b0_1000_0000,
			H	= 9'b1_0000_0000;

reg [8:0] state;

always @(posedge clk or posedge rst) begin : proc_flag
	if(rst) begin
		flag <= 1'b0;
		state <= IDLE;
	end else begin
		flag <= (state == H) ? 1'b1 : 1'b0;
		case (state)
			IDLE	:	state <= (din) ? IDLE : A;
			A 		:	state <= (din) ? B : A;
			B 		:	state <= (din) ? IDLE : C;
			C 		:	state <= (din) ? D : A;
			D 		:	state <= (din) ? IDLE : E;
			E 		:	state <= (din) ? F : A;
			F 		: 	state <= (din) ? IDLE : G;
			G 		:	state <= (din) ? H : A;
			H		:	state <= (din) ? IDLE : G;
		
			default : 	state <= IDLE;
		endcase
	end
end

endmodule

Digital System Design/Assignments/part_2/project2_G/mealy.v
//File: mealy.v

`timescale 1 ns / 100 ps 

module mealy (
	output reg flag,
	input din,
	input clk,
	input rst
	
);
parameter	IDLE= 9'b0_0000_0001,
			A	= 9'b0_0000_0010,
			B 	= 9'b0_0000_0100,
			C 	= 9'b0_0000_1000,
			D 	= 9'b0_0001_0000,
			E 	= 9'b0_0010_0000,
			F 	= 9'b0_0100_0000,
			G 	= 9'b0_1000_0000,
			H	= 9'b1_0000_0000;

reg [8:0] state;

always @(posedge clk or posedge rst) begin : proc_flag
	if(rst) begin
		flag <= 1'b0;
		state <= IDLE;
	end else begin
		case (state)
			IDLE	:	if(din) begin flag <= 1'b0; state <= IDLE; end
						else begin flag <= 1'b0; 	state <= A; end

			A 		:	if(din) begin flag <= 1'b0; state <= B; end
						else begin flag <= 1'b0;	state <= A; end

			B 		:	if(din) begin flag <= 1'b0; state <= IDLE; end
						else begin flag <= 1'b0;	state <= C; end

			C 		: 	if(din) begin flag <= 1'b0; state <= D; end
						else begin flag <= 1'b0; 	state <= A; end

			D 		: 	if(din) begin flag <= 1'b0; state <= IDLE; end
						else begin flag <= 1'b0; 	state <= E; end

			E    	:	if(din) begin flag <= 1'b0; state <= F; end
						else begin flag <= 1'b0; 	state <= A; end

			F 		:	if(din) begin flag <= 1'b0; state <= IDLE; end
						else begin flag <= 1'b0; 	state <= G; end

			G 		:	if(din) begin flag <= 1'b1; state <= H; end
						else begin flag <= 1'b0; 	state <= A; end

			H 		: 	if(din) begin flag <= 1'b0; state <= IDLE; end
						else begin flag <= 1'b0; 	state <= G; end
		
			default : 	begin flag <= 1'b0;	state <= IDLE; end
		endcase
	end
end

endmodule

Digital System Design/Assignments/part_2/project2_G/top.v
//File: top.v

`timescale 1 ns / 100 ps 
`include "mealy.v"
`include "moore.v"

module top;

	wire p_mlflag;
	wire p_mrflag;

	reg p_clk, p_rst, p_din;

	mealy meal(
		.flag (p_mlflag),
		.din  (p_din),
		.clk  (p_clk),
		.rst(p_rst)
		);

	moore moor(
		.flag (p_mrflag),
		.din  (p_din),
		.clk  (p_clk),
		.rst(p_rst)
		);

	initial begin 
		$dumpfile("mealy_moore.vcd");
		$dumpvars(0, top);

		p_rst = 1'b1;
		#25 p_rst = 1'b0;

		#250.5 p_rst = 1'b1;
		#5 p_rst = 1'b0;
	end

	initial begin 
		p_clk = 1'b0;
		forever begin 
			#10 p_clk = ~p_clk;
		end
	end

	parameter SIZE = 64;
	reg [SIZE - 1 : 0] data = 64'b0011_1011_0101_0101_0110_1010_1000_1101_1001_0101_0101_1010_1010_1010_1010_1010;

	initial begin : SERIES
		integer i;
		p_din = 1'b0;
		#30;
		for (i = 0; i < SIZE; i++) begin
			p_din = data[0];
			data = data >> 1;
			#20;
		end

		$stop;
	end

	initial begin 
		$display("At time %tns, reset = %b, datain = %b, mealy_flag = %b, moore_flag = %b.", $time, p_rst, p_din, p_mlflag, p_mrflag);
		forever begin 
			#20 $display("At time %tns, reset = %b, datain = %b, mealy_flag = %b, moore_flag = %b.", $time, p_rst, p_din, p_mlflag, p_mrflag);
		end
	end

endmodule

Digital System Design/Assignments/part_2/project2_G/mealy_moore.vcd
$date
	Fri Dec 13 21:26:59 2019
$end
$version
	Icarus Verilog
$end
$timescale
	100ps
$end
$scope module top $end
$var wire 1 ! p_mrflag $end
$var wire 1 " p_mlflag $end
$var reg 64 # data [63:0] $end
$var reg 1 $ p_clk $end
$var reg 1 % p_din $end
$var reg 1 & p_rst $end
$scope module meal $end
$var wire 1 $ clk $end
$var wire 1 % din $end
$var wire 1 & rst $end
$var reg 1 " flag $end
$var reg 9 ' state [8:0] $end
$scope begin proc_flag $end
$upscope $end
$upscope $end
$scope module moor $end
$var wire 1 $ clk $end
$var wire 1 % din $end
$var wire 1 & rst $end
$var reg 1 ! flag $end
$var reg 9 ( state [8:0] $end
$scope begin proc_flag $end
$upscope $end
$upscope $end
$scope begin SERIES $end
$var integer 32 ) i [31:0] $end
$upscope $end
$upscope $end
$enddefinitions $end
#0
$dumpvars
bx )
b1 (
b1 '
1&
0%
0$
b11101101010101011010101000110110010101010110101010101010101010 #
0"
0!
$end
#100
1$
#200
0$
#250
0&
#300
b10 (
b10 '
1$
b1110110101010101101010100011011001010101011010101010101010101 #
b0 )
#400
0$
#500
b100 (
b100 '
1$
b111011010101010110101010001101100101010101101010101010101010 #
1%
b1 )
#600
0$
#700
b1000 (
b1000 '
1$
b11101101010101011010101000110110010101010110101010101010101 #
0%
b10 )
#800
0$
#900
b10000 (
b10000 '
1$
b1110110101010101101010100011011001010101011010101010101010 #
1%
b11 )
#1000
0$
#1100
b100000 (
b100000 '
1$
b111011010101010110101010001101100101010101101010101010101 #
0%
b100 )
#1200
0$
#1300
b1000000 (
b1000000 '
1$
b11101101010101011010101000110110010101010110101010101010 #
1%
b101 )
#1400
0$
#1500
b10000000 (
b10000000 '
1$
b1110110101010101101010100011011001010101011010101010101 #
0%
b110 )
#1600
0$
#1700
b100000000 (
b100000000 '
1"
1$
b111011010101010110101010001101100101010101101010101010 #
1%
b111 )
#1800
0$
#1900
b10000000 (
1!
b10000000 '
0"
1$
b11101101010101011010101000110110010101010110101010101 #
0%
b1000 )
#2000
0$
#2100
b100000000 (
0!
b100000000 '
1"
1$
b1110110101010101101010100011011001010101011010101010 #
1%
b1001 )
#2200
0$
#2300
b10000000 (
1!
b10000000 '
0"
1$
b111011010101010110101010001101100101010101101010101 #
0%
b1010 )
#2400
0$
#2500
b100000000 (
0!
b100000000 '
1"
1$
b11101101010101011010101000110110010101010110101010 #
1%
b1011 )
#2600
0$
#2700
b10000000 (
1!
b10000000 '
0"
1$
b1110110101010101101010100011011001010101011010101 #
0%
b1100 )
#2755
b1 (
0!
b1 '
1&
#2800
0$
#2805
0&
#2900
1$
b111011010101010110101010001101100101010101101010 #
1%
b1101 )
#3000
0$
#3100
b10 (
b10 '
1$
b11101101010101011010101000110110010101010110101 #
0%
b1110 )
#3200
0$
#3300
b100 (
b100 '
1$
b1110110101010101101010100011011001010101011010 #
1%
b1111 )
#3400
0$
#3500
b1000 (
b1000 '
1$
b111011010101010110101010001101100101010101101 #
0%
b10000 )
#3600
0$
#3700
b10000 (
b10000 '
1$
b11101101010101011010101000110110010101010110 #
1%
b10001 )
#3800
0$
#3900
b100000 (
b100000 '
1$
b1110110101010101101010100011011001010101011 #
0%
b10010 )
#4000
0$
#4100
b1000000 (
b1000000 '
1$
b111011010101010110101010001101100101010101 #
1%
b10011 )
#4200
0$
#4300
b1 (
b1 '
1$
b11101101010101011010101000110110010101010 #
b10100 )
#4400
0$
#4500
b10 (
b10 '
1$
b1110110101010101101010100011011001010101 #
0%
b10101 )
#4600
0$
#4700
b100 (
b100 '
1$
b111011010101010110101010001101100101010 #
1%
b10110 )
#4800
0$
#4900
b1000 (
b1000 '
1$
b11101101010101011010101000110110010101 #
0%
b10111 )
#5000
0$
#5100
b10000 (
b10000 '
1$
b1110110101010101101010100011011001010 #
1%
b11000 )
#5200
0$
#5300
b100000 (
b100000 '
1$
b111011010101010110101010001101100101 #
0%
b11001 )
#5400
0$
#5500
b1000000 (
b1000000 '
1$
b11101101010101011010101000110110010 #
1%
b11010 )
#5600
0$
#5700
b10000000 (
b10000000 '
1$
b1110110101010101101010100011011001 #
0%
b11011 )
#5800
0$
#5900
b100000000 (
b100000000 '
1"
1$
b111011010101010110101010001101100 #
1%
b11100 )
#6000
0$
#6100
b10000000 (
1!
b10000000 '
0"
1$
b11101101010101011010101000110110 #
0%
b11101 )
#6200
0$
#6300
b10 (
0!
b10 '
1$
b1110110101010101101010100011011 #
b11110 )
#6400
0$
#6500
b100 (
b100 '
1$
b111011010101010110101010001101 #
1%
b11111 )
#6600
0$
#6700
b1 (
b1 '
1$
b11101101010101011010101000110 #
b100000 )
#6800
0$
#6900
b10 (
b10 '
1$
b1110110101010101101010100011 #
0%
b100001 )
#7000
0$
#7100
b100 (
b100 '
1$
b111011010101010110101010001 #
1%
b100010 )
#7200
0$
#7300
b1 (
b1 '
1$
b11101101010101011010101000 #
b100011 )
#7400
0$
#7500
b10 (
b10 '
1$
b1110110101010101101010100 #
0%
b100100 )
#7600
0$
#7700
1$
b111011010101010110101010 #
b100101 )
#7800
0$
#7900
1$
b11101101010101011010101 #
b100110 )
#8000
0$
#8100
b100 (
b100 '
1$
b1110110101010101101010 #
1%
b100111 )
#8200
0$
#8300
b1000 (
b1000 '
1$
b111011010101010110101 #
0%
b101000 )
#8400
0$
#8500
b10000 (
b10000 '
1$
b11101101010101011010 #
1%
b101001 )
#8600
0$
#8700
b100000 (
b100000 '
1$
b1110110101010101101 #
0%
b101010 )
#8800
0$
#8900
b1000000 (
b1000000 '
1$
b111011010101010110 #
1%
b101011 )
#9000
0$
#9100
b10000000 (
b10000000 '
1$
b11101101010101011 #
0%
b101100 )
#9200
0$
#9300
b100000000 (
b100000000 '
1"
1$
b1110110101010101 #
1%
b101101 )
#9400
0$
#9500
b1 (
1!
b1 '
0"
1$
b111011010101010 #
b101110 )
#9600
0$
#9700
b10 (
0!
b10 '
1$
b11101101010101 #
0%
b101111 )
#9800
0$
#9900
b100 (
b100 '
1$
b1110110101010 #
1%
b110000 )
#10000
0$
#10100
b1000 (
b1000 '
1$
b111011010101 #
0%
b110001 )
#10200
0$
#10300
b10000 (
b10000 '
1$
b11101101010 #
1%
b110010 )
#10400
0$
#10500
b100000 (
b100000 '
1$
b1110110101 #
0%
b110011 )
#10600
0$
#10700
b1000000 (
b1000000 '
1$
b111011010 #
1%
b110100 )
#10800
0$
#10900
b10000000 (
b10000000 '
1$
b11101101 #
0%
b110101 )
#11000
0$
#11100
b100000000 (
b100000000 '
1"
1$
b1110110 #
1%
b110110 )
#11200
0$
#11300
b10000000 (
1!
b10000000 '
0"
1$
b111011 #
0%
b110111 )
#11400
0$
#11500
b100000000 (
0!
b100000000 '
1"
1$
b11101 #
1%
b111000 )
#11600
0$
#11700
b1 (
1!
b1 '
0"
1$
b1110 #
b111001 )
#11800
0$
#11900
b10 (
0!
b10 '
1$
b111 #
0%
b111010 )
#12000
0$
#12100
b100 (
b100 '
1$
b11 #
1%
b111011 )
#12200
0$
#12300
b1 (
b1 '
1$
b1 #
b111100 )
#12400
0$
#12500
1$
b0 #
b111101 )
#12600
0$
#12700
b10 (
b10 '
1$
0%
b111110 )
#12800
0$
#12900
1$
b111111 )
